{
  "us_stocks": [
    {
      "symbol": "AAPL",
      "name": "Apple Inc.",
      "price": 333.26,
      "prev_close": 327.8,
      "change": 5.46,
      "change_pct": 1.67,
      "currency": "USD",
      "market": "US",
      "updated_at": "2026-07-16T20:12:57.334968Z"
    },
    {
      "symbol": "MSFT",
      "name": "Microsoft Corporation",
      "price": 401.1,
      "prev_close": 397.16,
      "change": 3.94,
      "change_pct": 0.99,
      "currency": "USD",
      "market": "US",
      "updated_at": "2026-07-16T20:12:57.896256Z"
    },
    {
      "symbol": "NVDA",
      "name": "NVIDIA Corporation",
      "price": 207.4,
      "prev_close": 211.25,
      "change": -3.85,
      "change_pct": -1.82,
      "currency": "USD",
      "market": "US",
      "updated_at": "2026-07-16T20:12:58.257437Z"
    },
    {
      "symbol": "GOOGL",
      "name": "Alphabet Inc.",
      "price": 354.46,
      "prev_close": 372.1,
      "change": -17.64,
      "change_pct": -4.74,
      "currency": "USD",
      "market": "US",
      "updated_at": "2026-07-16T20:12:58.591369Z"
    },
    {
      "symbol": "AMZN",
      "name": "Amazon.com, Inc.",
      "price": 249.89,
      "prev_close": 255.25,
      "change": -5.36,
      "change_pct": -2.1,
      "currency": "USD",
      "market": "US",
      "updated_at": "2026-07-16T20:12:58.924228Z"
    },
    {
      "symbol": "META",
      "name": "Meta Platforms, Inc.",
      "price": 664.54,
      "prev_close": 679.9,
      "change": -15.36,
      "change_pct": -2.26,
      "currency": "USD",
      "market": "US",
      "updated_at": "2026-07-16T20:12:59.383960Z"
    },
    {
      "symbol": "TSLA",
      "name": "Tesla, Inc.",
      "price": 391.06,
      "prev_close": 394.8,
      "change": -3.74,
      "change_pct": -0.95,
      "currency": "USD",
      "market": "US",
      "updated_at": "2026-07-16T20:12:59.776535Z"
    },
    {
      "symbol": "AVGO",
      "name": "Broadcom Inc.",
      "price": 374.45,
      "prev_close": 393.46,
      "change": -19.01,
      "change_pct": -4.83,
      "currency": "USD",
      "market": "US",
      "updated_at": "2026-07-16T20:13:00.111227Z"
    },
    {
      "symbol": "ORCL",
      "name": "Oracle Corporation",
      "price": 124.24,
      "prev_close": 133.08,
      "change": -8.84,
      "change_pct": -6.64,
      "currency": "USD",
      "market": "US",
      "updated_at": "2026-07-16T20:13:00.517207Z"
    },
    {
      "symbol": "NFLX",
      "name": "Netflix, Inc.",
      "price": 74.35,
      "prev_close": 73.98,
      "change": 0.37,
      "change_pct": 0.5,
      "currency": "USD",
      "market": "US",
      "updated_at": "2026-07-16T20:13:00.844183Z"
    },
    {
      "symbol": "AMD",
      "name": "Advanced Micro Devices, Inc.",
      "price": 500.94,
      "prev_close": 528.27,
      "change": -27.33,
      "change_pct": -5.17,
      "currency": "USD",
      "market": "US",
      "updated_at": "2026-07-16T20:13:01.158663Z"
    },
    {
      "symbol": "ADBE",
      "name": "Adobe Inc.",
      "price": 235.31,
      "prev_close": 224.86,
      "change": 10.45,
      "change_pct": 4.65,
      "currency": "USD",
      "market": "US",
      "updated_at": "2026-07-16T20:13:01.530934Z"
    },
    {
      "symbol": "CRM",
      "name": "Salesforce, Inc.",
      "price": 172.68,
      "prev_close": 167.6,
      "change": 5.08,
      "change_pct": 3.03,
      "currency": "USD",
      "market": "US",
      "updated_at": "2026-07-16T20:13:01.891139Z"
    },
    {
      "symbol": "INTC",
      "name": "Intel Corporation",
      "price": 96.98,
      "prev_close": 103.2,
      "change": -6.22,
      "change_pct": -6.03,
      "currency": "USD",
      "market": "US",
      "updated_at": "2026-07-16T20:13:02.333551Z"
    },
    {
      "symbol": "QCOM",
      "name": "QUALCOMM Incorporated",
      "price": 170.67,
      "prev_close": 178.25,
      "change": -7.58,
      "change_pct": -4.25,
      "currency": "USD",
      "market": "US",
      "updated_at": "2026-07-16T20:13:02.723283Z"
    },
    {
      "symbol": "TXN",
      "name": "Texas Instruments Incorporated",
      "price": 291.22,
      "prev_close": 300.6,
      "change": -9.38,
      "change_pct": -3.12,
      "currency": "USD",
      "market": "US",
      "updated_at": "2026-07-16T20:13:03.301898Z"
    },
    {
      "symbol": "AMAT",
      "name": "Applied Materials, Inc.",
      "price": 560.93,
      "prev_close": 581.75,
      "change": -20.82,
      "change_pct": -3.58,
      "currency": "USD",
      "market": "US",
      "updated_at": "2026-07-16T20:13:03.754405Z"
    },
    {
      "symbol": "MU",
      "name": "Micron Technology, Inc.",
      "price": 853.2,
      "prev_close": 896.1,
      "change": -42.9,
      "change_pct": -4.79,
      "currency": "USD",
      "market": "US",
      "updated_at": "2026-07-16T20:13:04.319151Z"
    },
    {
      "symbol": "KLAC",
      "name": "KLA Corporation",
      "price": 219.37,
      "prev_close": 224.8,
      "change": -5.43,
      "change_pct": -2.42,
      "currency": "USD",
      "market": "US",
      "updated_at": "2026-07-16T20:13:04.744318Z"
    },
    {
      "symbol": "LRCX",
      "name": "Lam Research Corporation",
      "price": 320.96,
      "prev_close": 335.75,
      "change": -14.79,
      "change_pct": -4.41,
      "currency": "USD",
      "market": "US",
      "updated_at": "2026-07-16T20:13:05.173219Z"
    },
    {
      "symbol": "BRK-B",
      "name": "Berkshire Hathaway Inc.",
      "price": 493.09,
      "prev_close": 489.19,
      "change": 3.9,
      "change_pct": 0.8,
      "currency": "USD",
      "market": "US",
      "updated_at": "2026-07-16T20:13:06.639437Z"
    },
    {
      "symbol": "JPM",
      "name": "JPMorgan Chase & Co.",
      "price": 343.16,
      "prev_close": 347.31,
      "change": -4.15,
      "change_pct": -1.19,
      "currency": "USD",
      "market": "US",
      "updated_at": "2026-07-16T20:13:07.301544Z"
    },
    {
      "symbol": "V",
      "name": "Visa Inc.",
      "price": 364.81,
      "prev_close": 355.44,
      "change": 9.37,
      "change_pct": 2.64,
      "currency": "USD",
      "market": "US",
      "updated_at": "2026-07-16T20:13:07.717378Z"
    },
    {
      "symbol": "MA",
      "name": "Mastercard Incorporated",
      "price": 551.49,
      "prev_close": 539.26,
      "change": 12.23,
      "change_pct": 2.27,
      "currency": "USD",
      "market": "US",
      "updated_at": "2026-07-16T20:13:08.109765Z"
    },
    {
      "symbol": "BAC",
      "name": "Bank of America Corporation",
      "price": 61.51,
      "prev_close": 61.6,
      "change": -0.09,
      "change_pct": -0.15,
      "currency": "USD",
      "market": "US",
      "updated_at": "2026-07-16T20:13:08.574832Z"
    },
    {
      "symbol": "GS",
      "name": "The Goldman Sachs Group, Inc.",
      "price": 1095.86,
      "prev_close": 1151.25,
      "change": -55.39,
      "change_pct": -4.81,
      "currency": "USD",
      "market": "US",
      "updated_at": "2026-07-16T20:13:09.034148Z"
    },
    {
      "symbol": "MS",
      "name": "Morgan Stanley",
      "price": 218.28,
      "prev_close": 228.12,
      "change": -9.84,
      "change_pct": -4.31,
      "currency": "USD",
      "market": "US",
      "updated_at": "2026-07-16T20:13:09.464536Z"
    },
    {
      "symbol": "WFC",
      "name": "Wells Fargo & Company",
      "price": 88.07,
      "prev_close": 87.69,
      "change": 0.38,
      "change_pct": 0.43,
      "currency": "USD",
      "market": "US",
      "updated_at": "2026-07-16T20:13:10.196441Z"
    },
    {
      "symbol": "AXP",
      "name": "American Express Company",
      "price": 361.56,
      "prev_close": 360.0,
      "change": 1.56,
      "change_pct": 0.43,
      "currency": "USD",
      "market": "US",
      "updated_at": "2026-07-16T20:13:10.678892Z"
    },
    {
      "symbol": "BLK",
      "name": "BlackRock, Inc.",
      "price": 1087.24,
      "prev_close": 1088.08,
      "change": -0.84,
      "change_pct": -0.08,
      "currency": "USD",
      "market": "US",
      "updated_at": "2026-07-16T20:13:11.136483Z"
    },
    {
      "symbol": "SCHW",
      "name": "The Charles Schwab Corporation",
      "price": 102.8,
      "prev_close": 103.41,
      "change": -0.61,
      "change_pct": -0.59,
      "currency": "USD",
      "market": "US",
      "updated_at": "2026-07-16T20:13:11.530762Z"
    },
    {
      "symbol": "C",
      "name": "Citigroup Inc.",
      "price": 131.71,
      "prev_close": 134.55,
      "change": -2.84,
      "change_pct": -2.11,
      "currency": "USD",
      "market": "US",
      "updated_at": "2026-07-16T20:13:11.970344Z"
    },
    {
      "symbol": "SPGI",
      "name": "S&P Global Inc.",
      "price": 457.38,
      "prev_close": 444.45,
      "change": 12.93,
      "change_pct": 2.91,
      "currency": "USD",
      "market": "US",
      "updated_at": "2026-07-16T20:13:12.467070Z"
    },
    {
      "symbol": "MCO",
      "name": "Moody's Corporation",
      "price": 518.9,
      "prev_close": 494.62,
      "change": 24.28,
      "change_pct": 4.91,
      "currency": "USD",
      "market": "US",
      "updated_at": "2026-07-16T20:13:12.907275Z"
    },
    {
      "symbol": "COF",
      "name": "Capital One Financial Corporation",
      "price": 211.96,
      "prev_close": 208.94,
      "change": 3.02,
      "change_pct": 1.45,
      "currency": "USD",
      "market": "US",
      "updated_at": "2026-07-16T20:13:13.303773Z"
    },
    {
      "symbol": "LLY",
      "name": "Eli Lilly and Company",
      "price": 1170.23,
      "prev_close": 1157.99,
      "change": 12.24,
      "change_pct": 1.06,
      "currency": "USD",
      "market": "US",
      "updated_at": "2026-07-16T20:13:13.854830Z"
    },
    {
      "symbol": "UNH",
      "name": "UnitedHealth Group Incorporated",
      "price": 423.41,
      "prev_close": 415.7,
      "change": 7.71,
      "change_pct": 1.85,
      "currency": "USD",
      "market": "US",
      "updated_at": "2026-07-16T20:13:14.303152Z"
    },
    {
      "symbol": "JNJ",
      "name": "Johnson & Johnson",
      "price": 249.6,
      "prev_close": 247.9,
      "change": 1.7,
      "change_pct": 0.69,
      "currency": "USD",
      "market": "US",
      "updated_at": "2026-07-16T20:13:14.877898Z"
    },
    {
      "symbol": "ABBV",
      "name": "AbbVie Inc.",
      "price": 254.37,
      "prev_close": 244.78,
      "change": 9.59,
      "change_pct": 3.92,
      "currency": "USD",
      "market": "US",
      "updated_at": "2026-07-16T20:13:15.256221Z"
    },
    {
      "symbol": "MRK",
      "name": "Merck & Co., Inc.",
      "price": 127.68,
      "prev_close": 123.41,
      "change": 4.27,
      "change_pct": 3.46,
      "currency": "USD",
      "market": "US",
      "updated_at": "2026-07-16T20:13:15.744721Z"
    },
    {
      "symbol": "TMO",
      "name": "Thermo Fisher Scientific Inc.",
      "price": 543.0,
      "prev_close": 529.25,
      "change": 13.75,
      "change_pct": 2.6,
      "currency": "USD",
      "market": "US",
      "updated_at": "2026-07-16T20:13:17.182458Z"
    },
    {
      "symbol": "ABT",
      "name": "Abbott Laboratories",
      "price": 98.82,
      "prev_close": 89.79,
      "change": 9.03,
      "change_pct": 10.06,
      "currency": "USD",
      "market": "US",
      "updated_at": "2026-07-16T20:13:17.691116Z"
    },
    {
      "symbol": "DHR",
      "name": "Danaher Corporation",
      "price": 204.99,
      "prev_close": 201.8,
      "change": 3.19,
      "change_pct": 1.58,
      "currency": "USD",
      "market": "US",
      "updated_at": "2026-07-16T20:13:18.122481Z"
    },
    {
      "symbol": "AMGN",
      "name": "Amgen Inc.",
      "price": 371.58,
      "prev_close": 358.43,
      "change": 13.15,
      "change_pct": 3.67,
      "currency": "USD",
      "market": "US",
      "updated_at": "2026-07-16T20:13:18.524025Z"
    },
    {
      "symbol": "ISRG",
      "name": "Intuitive Surgical, Inc.",
      "price": 402.33,
      "prev_close": 389.23,
      "change": 13.1,
      "change_pct": 3.37,
      "currency": "USD",
      "market": "US",
      "updated_at": "2026-07-16T20:13:18.935207Z"
    },
    {
      "symbol": "GILD",
      "name": "Gilead Sciences, Inc.",
      "price": 136.3,
      "prev_close": 129.02,
      "change": 7.28,
      "change_pct": 5.64,
      "currency": "USD",
      "market": "US",
      "updated_at": "2026-07-16T20:13:19.426346Z"
    },
    {
      "symbol": "VRTX",
      "name": "Vertex Pharmaceuticals Incorporated",
      "price": 486.03,
      "prev_close": 478.0,
      "change": 8.03,
      "change_pct": 1.68,
      "currency": "USD",
      "market": "US",
      "updated_at": "2026-07-16T20:13:19.873163Z"
    },
    {
      "symbol": "REGN",
      "name": "Regeneron Pharmaceuticals, Inc.",
      "price": 678.94,
      "prev_close": 672.0,
      "change": 6.94,
      "change_pct": 1.03,
      "currency": "USD",
      "market": "US",
      "updated_at": "2026-07-16T20:13:20.203073Z"
    },
    {
      "symbol": "BSX",
      "name": "Boston Scientific Corporation",
      "price": 44.62,
      "prev_close": 43.15,
      "change": 1.47,
      "change_pct": 3.41,
      "currency": "USD",
      "market": "US",
      "updated_at": "2026-07-16T20:13:20.525961Z"
    },
    {
      "symbol": "SYK",
      "name": "Stryker Corporation",
      "price": 331.03,
      "prev_close": 313.0,
      "change": 18.03,
      "change_pct": 5.76,
      "currency": "USD",
      "market": "US",
      "updated_at": "2026-07-16T20:13:20.926311Z"
    },
    {
      "symbol": "COST",
      "name": "Costco Wholesale Corporation",
      "price": 945.57,
      "prev_close": 916.75,
      "change": 28.82,
      "change_pct": 3.14,
      "currency": "USD",
      "market": "US",
      "updated_at": "2026-07-16T20:13:21.260022Z"
    },
    {
      "symbol": "WMT",
      "name": "Walmart Inc.",
      "price": 114.95,
      "prev_close": 112.85,
      "change": 2.1,
      "change_pct": 1.86,
      "currency": "USD",
      "market": "US",
      "updated_at": "2026-07-16T20:13:21.710777Z"
    },
    {
      "symbol": "HD",
      "name": "The Home Depot, Inc.",
      "price": 347.84,
      "prev_close": 339.95,
      "change": 7.89,
      "change_pct": 2.32,
      "currency": "USD",
      "market": "US",
      "updated_at": "2026-07-16T20:13:22.117520Z"
    },
    {
      "symbol": "MCD",
      "name": "McDonald's Corporation",
      "price": 273.43,
      "prev_close": 265.29,
      "change": 8.14,
      "change_pct": 3.07,
      "currency": "USD",
      "market": "US",
      "updated_at": "2026-07-16T20:13:22.599027Z"
    },
    {
      "symbol": "SBUX",
      "name": "Starbucks Corporation",
      "price": 108.37,
      "prev_close": 104.65,
      "change": 3.72,
      "change_pct": 3.55,
      "currency": "USD",
      "market": "US",
      "updated_at": "2026-07-16T20:13:22.931972Z"
    },
    {
      "symbol": "NKE",
      "name": "NIKE, Inc.",
      "price": 44.55,
      "prev_close": 42.82,
      "change": 1.73,
      "change_pct": 4.04,
      "currency": "USD",
      "market": "US",
      "updated_at": "2026-07-16T20:13:23.389243Z"
    },
    {
      "symbol": "LOW",
      "name": "Lowe's Companies, Inc.",
      "price": 216.19,
      "prev_close": 210.0,
      "change": 6.19,
      "change_pct": 2.95,
      "currency": "USD",
      "market": "US",
      "updated_at": "2026-07-16T20:13:23.821682Z"
    },
    {
      "symbol": "TGT",
      "name": "Target Corporation",
      "price": 140.21,
      "prev_close": 138.84,
      "change": 1.37,
      "change_pct": 0.99,
      "currency": "USD",
      "market": "US",
      "updated_at": "2026-07-16T20:13:24.542106Z"
    },
    {
      "symbol": "BKNG",
      "name": "Booking Holdings Inc.",
      "price": 184.61,
      "prev_close": 182.8,
      "change": 1.81,
      "change_pct": 0.99,
      "currency": "USD",
      "market": "US",
      "updated_at": "2026-07-16T20:13:24.905179Z"
    },
    {
      "symbol": "MAR",
      "name": "Marriott International, Inc.",
      "price": 371.14,
      "prev_close": 370.54,
      "change": 0.6,
      "change_pct": 0.16,
      "currency": "USD",
      "market": "US",
      "updated_at": "2026-07-16T20:13:25.372216Z"
    },
    {
      "symbol": "HLT",
      "name": "Hilton Worldwide Holdings Inc.",
      "price": 323.2,
      "prev_close": 327.99,
      "change": -4.79,
      "change_pct": -1.46,
      "currency": "USD",
      "market": "US",
      "updated_at": "2026-07-16T20:13:26.801912Z"
    },
    {
      "symbol": "XOM",
      "name": "ExxonMobil Holdings Corporation",
      "price": 145.95,
      "prev_close": 144.41,
      "change": 1.54,
      "change_pct": 1.07,
      "currency": "USD",
      "market": "US",
      "updated_at": "2026-07-16T20:13:27.333736Z"
    },
    {
      "symbol": "CVX",
      "name": "Chevron Corporation",
      "price": 183.88,
      "prev_close": 181.28,
      "change": 2.6,
      "change_pct": 1.43,
      "currency": "USD",
      "market": "US",
      "updated_at": "2026-07-16T20:13:27.974080Z"
    },
    {
      "symbol": "CAT",
      "name": "Caterpillar Inc.",
      "price": 877.77,
      "prev_close": 914.78,
      "change": -37.01,
      "change_pct": -4.05,
      "currency": "USD",
      "market": "US",
      "updated_at": "2026-07-16T20:13:28.590280Z"
    },
    {
      "symbol": "GE",
      "name": "GE Aerospace",
      "price": 345.67,
      "prev_close": 360.84,
      "change": -15.17,
      "change_pct": -4.2,
      "currency": "USD",
      "market": "US",
      "updated_at": "2026-07-16T20:13:29.193325Z"
    },
    {
      "symbol": "BA",
      "name": "The Boeing Company",
      "price": 214.33,
      "prev_close": 218.13,
      "change": -3.8,
      "change_pct": -1.74,
      "currency": "USD",
      "market": "US",
      "updated_at": "2026-07-16T20:13:29.767446Z"
    },
    {
      "symbol": "RTX",
      "name": "RTX Corporation",
      "price": 194.35,
      "prev_close": 195.81,
      "change": -1.46,
      "change_pct": -0.75,
      "currency": "USD",
      "market": "US",
      "updated_at": "2026-07-16T20:13:30.278823Z"
    },
    {
      "symbol": "HON",
      "name": "Honeywell International Inc.",
      "price": 226.33,
      "prev_close": 224.72,
      "change": 1.61,
      "change_pct": 0.72,
      "currency": "USD",
      "market": "US",
      "updated_at": "2026-07-16T20:13:30.802124Z"
    },
    {
      "symbol": "UPS",
      "name": "United Parcel Service, Inc.",
      "price": 117.18,
      "prev_close": 112.94,
      "change": 4.24,
      "change_pct": 3.75,
      "currency": "USD",
      "market": "US",
      "updated_at": "2026-07-16T20:13:31.192503Z"
    },
    {
      "symbol": "LMT",
      "name": "Lockheed Martin Corporation",
      "price": 513.34,
      "prev_close": 514.0,
      "change": -0.66,
      "change_pct": -0.13,
      "currency": "USD",
      "market": "US",
      "updated_at": "2026-07-16T20:13:31.693153Z"
    },
    {
      "symbol": "DE",
      "name": "Deere & Company",
      "price": 598.88,
      "prev_close": 584.75,
      "change": 14.13,
      "change_pct": 2.42,
      "currency": "USD",
      "market": "US",
      "updated_at": "2026-07-16T20:13:32.208974Z"
    },
    {
      "symbol": "DIS",
      "name": "The Walt Disney Company",
      "price": 99.72,
      "prev_close": 97.06,
      "change": 2.66,
      "change_pct": 2.74,
      "currency": "USD",
      "market": "US",
      "updated_at": "2026-07-16T20:13:32.704323Z"
    },
    {
      "symbol": "CMCSA",
      "name": "Comcast Corporation",
      "price": 24.1,
      "prev_close": 23.5,
      "change": 0.6,
      "change_pct": 2.55,
      "currency": "USD",
      "market": "US",
      "updated_at": "2026-07-16T20:13:33.184462Z"
    },
    {
      "symbol": "T",
      "name": "AT&T Inc.",
      "price": 21.99,
      "prev_close": 21.41,
      "change": 0.58,
      "change_pct": 2.71,
      "currency": "USD",
      "market": "US",
      "updated_at": "2026-07-16T20:13:33.661332Z"
    },
    {
      "symbol": "VZ",
      "name": "Verizon Communications Inc.",
      "price": 43.87,
      "prev_close": 42.84,
      "change": 1.03,
      "change_pct": 2.4,
      "currency": "USD",
      "market": "US",
      "updated_at": "2026-07-16T20:13:34.178473Z"
    },
    {
      "symbol": "TMUS",
      "name": "T-Mobile US, Inc.",
      "price": 192.85,
      "prev_close": 187.09,
      "change": 5.76,
      "change_pct": 3.08,
      "currency": "USD",
      "market": "US",
      "updated_at": "2026-07-16T20:13:34.508027Z"
    },
    {
      "symbol": "PYPL",
      "name": "PayPal Holdings, Inc.",
      "price": 56.73,
      "prev_close": 55.3,
      "change": 1.43,
      "change_pct": 2.59,
      "currency": "USD",
      "market": "US",
      "updated_at": "2026-07-16T20:13:34.880964Z"
    },
    {
      "symbol": "UBER",
      "name": "Uber Technologies, Inc.",
      "price": 74.04,
      "prev_close": 72.7,
      "change": 1.34,
      "change_pct": 1.84,
      "currency": "USD",
      "market": "US",
      "updated_at": "2026-07-16T20:13:35.224236Z"
    },
    {
      "symbol": "ABNB",
      "name": "Airbnb, Inc.",
      "price": 147.8,
      "prev_close": 148.12,
      "change": -0.32,
      "change_pct": -0.22,
      "currency": "USD",
      "market": "US",
      "updated_at": "2026-07-16T20:13:35.547249Z"
    },
    {
      "symbol": "SNOW",
      "name": "Snowflake Inc.",
      "price": 270.05,
      "prev_close": 272.0,
      "change": -1.95,
      "change_pct": -0.72,
      "currency": "USD",
      "market": "US",
      "updated_at": "2026-07-16T20:13:35.842463Z"
    },
    {
      "symbol": "PLTR",
      "name": "Palantir Technologies Inc.",
      "price": 134.44,
      "prev_close": 133.76,
      "change": 0.68,
      "change_pct": 0.51,
      "currency": "USD",
      "market": "US",
      "updated_at": "2026-07-16T20:13:37.406594Z"
    },
    {
      "symbol": "COIN",
      "name": "Coinbase Global, Inc.",
      "price": 160.49,
      "prev_close": 166.39,
      "change": -5.9,
      "change_pct": -3.55,
      "currency": "USD",
      "market": "US",
      "updated_at": "2026-07-16T20:13:37.708005Z"
    },
    {
      "symbol": "SHOP",
      "name": "Shopify Inc.",
      "price": 125.06,
      "prev_close": 123.4,
      "change": 1.66,
      "change_pct": 1.35,
      "currency": "USD",
      "market": "US",
      "updated_at": "2026-07-16T20:13:38.286707Z"
    },
    {
      "symbol": "ZM",
      "name": "Zoom Communications, Inc.",
      "price": 92.92,
      "prev_close": 92.7,
      "change": 0.22,
      "change_pct": 0.24,
      "currency": "USD",
      "market": "US",
      "updated_at": "2026-07-16T20:13:38.620848Z"
    },
    {
      "symbol": "ROKU",
      "name": "Roku, Inc.",
      "price": 143.82,
      "prev_close": 143.03,
      "change": 0.79,
      "change_pct": 0.55,
      "currency": "USD",
      "market": "US",
      "updated_at": "2026-07-16T20:13:38.959204Z"
    },
    {
      "symbol": "RBLX",
      "name": "Roblox Corporation",
      "price": 54.04,
      "prev_close": 56.9,
      "change": -2.86,
      "change_pct": -5.03,
      "currency": "USD",
      "market": "US",
      "updated_at": "2026-07-16T20:13:39.273361Z"
    },
    {
      "symbol": "HOOD",
      "name": "Robinhood Markets, Inc.",
      "price": 106.02,
      "prev_close": 115.72,
      "change": -9.7,
      "change_pct": -8.38,
      "currency": "USD",
      "market": "US",
      "updated_at": "2026-07-16T20:13:39.640191Z"
    },
    {
      "symbol": "RIVN",
      "name": "Rivian Automotive, Inc.",
      "price": 17.09,
      "prev_close": 17.79,
      "change": -0.7,
      "change_pct": -3.93,
      "currency": "USD",
      "market": "US",
      "updated_at": "2026-07-16T20:13:39.961301Z"
    },
    {
      "symbol": "LCID",
      "name": "Lucid Group, Inc.",
      "price": 6.46,
      "prev_close": 5.85,
      "change": 0.61,
      "change_pct": 10.43,
      "currency": "USD",
      "market": "US",
      "updated_at": "2026-07-16T20:13:40.313699Z"
    },
    {
      "symbol": "SPY",
      "name": "State Street SPDR S&P 500 ETF Trust",
      "price": 750.77,
      "prev_close": 754.68,
      "change": -3.91,
      "change_pct": -0.52,
      "currency": "USD",
      "market": "US",
      "updated_at": "2026-07-16T20:13:40.713734Z"
    },
    {
      "symbol": "QQQ",
      "name": "Invesco QQQ Trust",
      "price": 705.94,
      "prev_close": 717.41,
      "change": -11.47,
      "change_pct": -1.6,
      "currency": "USD",
      "market": "US",
      "updated_at": "2026-07-16T20:13:41.118160Z"
    },
    {
      "symbol": "DIA",
      "name": "State Street SPDR Dow Jones Industrial A",
      "price": 524.78,
      "prev_close": 526.0,
      "change": -1.22,
      "change_pct": -0.23,
      "currency": "USD",
      "market": "US",
      "updated_at": "2026-07-16T20:13:41.523013Z"
    },
    {
      "symbol": "VTI",
      "name": "Vanguard Total Stock Market Index Fund E",
      "price": 370.61,
      "prev_close": 372.4,
      "change": -1.79,
      "change_pct": -0.48,
      "currency": "USD",
      "market": "US",
      "updated_at": "2026-07-16T20:13:41.917222Z"
    },
    {
      "symbol": "IWM",
      "name": "iShares Russell 2000 ETF",
      "price": 295.6,
      "prev_close": 295.82,
      "change": -0.22,
      "change_pct": -0.07,
      "currency": "USD",
      "market": "US",
      "updated_at": "2026-07-16T20:13:42.394994Z"
    },
    {
      "symbol": "TSM",
      "name": "Taiwan Semiconductor Manufacturing Compa",
      "price": 410.05,
      "prev_close": 423.48,
      "change": -13.43,
      "change_pct": -3.17,
      "currency": "USD",
      "market": "US",
      "updated_at": "2026-07-16T20:13:42.764996Z"
    },
    {
      "symbol": "UMC",
      "name": "United Microelectronics Corporation",
      "price": 22.39,
      "prev_close": 24.77,
      "change": -2.38,
      "change_pct": -9.61,
      "currency": "USD",
      "market": "US",
      "updated_at": "2026-07-16T20:13:43.164418Z"
    }
  ],
  "tw_stocks": [
    {
      "symbol": "2330",
      "name": "Taiwan Semiconductor",
      "price": 2470.0,
      "prev_close": 2455.0,
      "change": 15.0,
      "change_pct": 0.61,
      "currency": "TWD",
      "market": "TW",
      "updated_at": "2026-07-16T20:13:59.572134Z"
    },
    {
      "symbol": "2317",
      "name": "Hon Hai Precision In",
      "price": 242.5,
      "prev_close": 240.5,
      "change": 2.0,
      "change_pct": 0.83,
      "currency": "TWD",
      "market": "TW",
      "updated_at": "2026-07-16T20:14:00.000412Z"
    },
    {
      "symbol": "2454",
      "name": "MediaTek Inc.",
      "price": 3700.0,
      "prev_close": 3755.0,
      "change": -55.0,
      "change_pct": -1.46,
      "currency": "TWD",
      "market": "TW",
      "updated_at": "2026-07-16T20:14:00.402035Z"
    },
    {
      "symbol": "2382",
      "name": "Quanta Computer Inc.",
      "price": 352.0,
      "prev_close": 381.0,
      "change": -29.0,
      "change_pct": -7.61,
      "currency": "TWD",
      "market": "TW",
      "updated_at": "2026-07-16T20:14:00.817368Z"
    },
    {
      "symbol": "2308",
      "name": "Delta Electronics, I",
      "price": 1905.0,
      "prev_close": 1905.0,
      "change": 0.0,
      "change_pct": 0.0,
      "currency": "TWD",
      "market": "TW",
      "updated_at": "2026-07-16T20:14:01.192717Z"
    },
    {
      "symbol": "2303",
      "name": "United Microelectron",
      "price": 160.0,
      "prev_close": 165.5,
      "change": -5.5,
      "change_pct": -3.32,
      "currency": "TWD",
      "market": "TW",
      "updated_at": "2026-07-16T20:14:01.621252Z"
    },
    {
      "symbol": "2881",
      "name": "Fubon Financial Hold",
      "price": 125.0,
      "prev_close": 129.5,
      "change": -4.5,
      "change_pct": -3.47,
      "currency": "TWD",
      "market": "TW",
      "updated_at": "2026-07-16T20:14:02.200993Z"
    },
    {
      "symbol": "2882",
      "name": "Cathay Financial Hol",
      "price": 97.3,
      "prev_close": 96.9,
      "change": 0.4,
      "change_pct": 0.41,
      "currency": "TWD",
      "market": "TW",
      "updated_at": "2026-07-16T20:14:02.609893Z"
    },
    {
      "symbol": "2891",
      "name": "CTBC Financial Holdi",
      "price": 63.0,
      "prev_close": 63.6,
      "change": -0.6,
      "change_pct": -0.94,
      "currency": "TWD",
      "market": "TW",
      "updated_at": "2026-07-16T20:14:03.023972Z"
    },
    {
      "symbol": "2886",
      "name": "Mega Financial Holdi",
      "price": 46.6,
      "prev_close": 46.05,
      "change": 0.55,
      "change_pct": 1.19,
      "currency": "TWD",
      "market": "TW",
      "updated_at": "2026-07-16T20:14:03.395847Z"
    },
    {
      "symbol": "2884",
      "name": "E.SUN Financial Hold",
      "price": 34.9,
      "prev_close": 34.6,
      "change": 0.3,
      "change_pct": 0.87,
      "currency": "TWD",
      "market": "TW",
      "updated_at": "2026-07-16T20:14:04.744914Z"
    },
    {
      "symbol": "2885",
      "name": "Yuanta Financial Hol",
      "price": 66.7,
      "prev_close": 67.3,
      "change": -0.6,
      "change_pct": -0.89,
      "currency": "TWD",
      "market": "TW",
      "updated_at": "2026-07-16T20:14:05.155959Z"
    },
    {
      "symbol": "2892",
      "name": "First Financial Hold",
      "price": 33.95,
      "prev_close": 33.2,
      "change": 0.75,
      "change_pct": 2.26,
      "currency": "TWD",
      "market": "TW",
      "updated_at": "2026-07-16T20:14:05.707478Z"
    },
    {
      "symbol": "2883",
      "name": "KGI Financial Holdin",
      "price": 30.55,
      "prev_close": 30.15,
      "change": 0.4,
      "change_pct": 1.33,
      "currency": "TWD",
      "market": "TW",
      "updated_at": "2026-07-16T20:14:06.194530Z"
    },
    {
      "symbol": "2887",
      "name": "TS Financial Holding",
      "price": 36.15,
      "prev_close": 36.2,
      "change": -0.05,
      "change_pct": -0.14,
      "currency": "TWD",
      "market": "TW",
      "updated_at": "2026-07-16T20:14:06.602094Z"
    },
    {
      "symbol": "2412",
      "name": "Chunghwa Telecom Co.",
      "price": 136.0,
      "prev_close": 133.0,
      "change": 3.0,
      "change_pct": 2.26,
      "currency": "TWD",
      "market": "TW",
      "updated_at": "2026-07-16T20:14:07.805538Z"
    },
    {
      "symbol": "2002",
      "name": "China Steel Corporat",
      "price": 18.8,
      "prev_close": 18.65,
      "change": 0.15,
      "change_pct": 0.8,
      "currency": "TWD",
      "market": "TW",
      "updated_at": "2026-07-16T20:14:08.732816Z"
    },
    {
      "symbol": "1301",
      "name": "Formosa Plastics Cor",
      "price": 65.6,
      "prev_close": 65.7,
      "change": -0.1,
      "change_pct": -0.15,
      "currency": "TWD",
      "market": "TW",
      "updated_at": "2026-07-16T20:14:09.241822Z"
    },
    {
      "symbol": "1303",
      "name": "Nan Ya Plastics Corp",
      "price": 221.0,
      "prev_close": 226.5,
      "change": -5.5,
      "change_pct": -2.43,
      "currency": "TWD",
      "market": "TW",
      "updated_at": "2026-07-16T20:14:09.620877Z"
    },
    {
      "symbol": "1326",
      "name": "Formosa Chemicals & ",
      "price": 68.9,
      "prev_close": 70.9,
      "change": -2.0,
      "change_pct": -2.82,
      "currency": "TWD",
      "market": "TW",
      "updated_at": "2026-07-16T20:14:10.977954Z"
    },
    {
      "symbol": "2207",
      "name": "Hotai Motor Co.,Ltd.",
      "price": 493.0,
      "prev_close": 482.5,
      "change": 10.5,
      "change_pct": 2.18,
      "currency": "TWD",
      "market": "TW",
      "updated_at": "2026-07-16T20:14:11.634681Z"
    },
    {
      "symbol": "2357",
      "name": "ASUSTeK Computer Inc",
      "price": 715.0,
      "prev_close": 714.0,
      "change": 1.0,
      "change_pct": 0.14,
      "currency": "TWD",
      "market": "TW",
      "updated_at": "2026-07-16T20:14:12.223874Z"
    },
    {
      "symbol": "2379",
      "name": "Realtek Semiconducto",
      "price": 712.0,
      "prev_close": 761.0,
      "change": -49.0,
      "change_pct": -6.44,
      "currency": "TWD",
      "market": "TW",
      "updated_at": "2026-07-16T20:14:12.640911Z"
    },
    {
      "symbol": "2395",
      "name": "Advantech Co., Ltd.",
      "price": 530.0,
      "prev_close": 533.0,
      "change": -3.0,
      "change_pct": -0.56,
      "currency": "TWD",
      "market": "TW",
      "updated_at": "2026-07-16T20:14:13.084484Z"
    },
    {
      "symbol": "3711",
      "name": "ASE Technology Holdi",
      "price": 682.0,
      "prev_close": 685.0,
      "change": -3.0,
      "change_pct": -0.44,
      "currency": "TWD",
      "market": "TW",
      "updated_at": "2026-07-16T20:14:13.473082Z"
    },
    {
      "symbol": "2376",
      "name": "Giga-Byte Technology",
      "price": 337.0,
      "prev_close": 344.5,
      "change": -7.5,
      "change_pct": -2.18,
      "currency": "TWD",
      "market": "TW",
      "updated_at": "2026-07-16T20:14:13.947558Z"
    },
    {
      "symbol": "2408",
      "name": "Nanya Technology Cor",
      "price": 439.0,
      "prev_close": 480.5,
      "change": -41.5,
      "change_pct": -8.64,
      "currency": "TWD",
      "market": "TW",
      "updated_at": "2026-07-16T20:14:14.362225Z"
    },
    {
      "symbol": "3008",
      "name": "Largan Precision Co.",
      "price": 4260.0,
      "prev_close": 4065.0,
      "change": 195.0,
      "change_pct": 4.8,
      "currency": "TWD",
      "market": "TW",
      "updated_at": "2026-07-16T20:14:14.790617Z"
    },
    {
      "symbol": "2327",
      "name": "Yageo Corporation",
      "price": 776.0,
      "prev_close": 797.0,
      "change": -21.0,
      "change_pct": -2.63,
      "currency": "TWD",
      "market": "TW",
      "updated_at": "2026-07-16T20:14:15.330851Z"
    },
    {
      "symbol": "4938",
      "name": "Pegatron Corporation",
      "price": 83.2,
      "prev_close": 82.7,
      "change": 0.5,
      "change_pct": 0.6,
      "currency": "TWD",
      "market": "TW",
      "updated_at": "2026-07-16T20:14:17.174918Z"
    },
    {
      "symbol": "2337",
      "name": "Macronix Internation",
      "price": 136.5,
      "prev_close": 149.0,
      "change": -12.5,
      "change_pct": -8.39,
      "currency": "TWD",
      "market": "TW",
      "updated_at": "2026-07-16T20:14:17.551717Z"
    },
    {
      "symbol": "2344",
      "name": "Winbond Electronics ",
      "price": 172.0,
      "prev_close": 180.5,
      "change": -8.5,
      "change_pct": -4.71,
      "currency": "TWD",
      "market": "TW",
      "updated_at": "2026-07-16T20:14:17.918277Z"
    },
    {
      "symbol": "2345",
      "name": "Accton Technology Co",
      "price": 2320.0,
      "prev_close": 2350.0,
      "change": -30.0,
      "change_pct": -1.28,
      "currency": "TWD",
      "market": "TW",
      "updated_at": "2026-07-16T20:14:18.317489Z"
    },
    {
      "symbol": "3034",
      "name": "Novatek Microelectro",
      "price": 471.5,
      "prev_close": 472.0,
      "change": -0.5,
      "change_pct": -0.11,
      "currency": "TWD",
      "market": "TW",
      "updated_at": "2026-07-16T20:14:18.737750Z"
    },
    {
      "symbol": "3037",
      "name": "Unimicron Technology",
      "price": 882.0,
      "prev_close": 940.0,
      "change": -58.0,
      "change_pct": -6.17,
      "currency": "TWD",
      "market": "TW",
      "updated_at": "2026-07-16T20:14:19.295696Z"
    },
    {
      "symbol": "3045",
      "name": "Taiwan Mobile Co., L",
      "price": 110.5,
      "prev_close": 109.0,
      "change": 1.5,
      "change_pct": 1.38,
      "currency": "TWD",
      "market": "TW",
      "updated_at": "2026-07-16T20:14:19.704749Z"
    },
    {
      "symbol": "3231",
      "name": "Wistron Corporation",
      "price": 146.5,
      "prev_close": 146.5,
      "change": 0.0,
      "change_pct": 0.0,
      "currency": "TWD",
      "market": "TW",
      "updated_at": "2026-07-16T20:14:20.104304Z"
    },
    {
      "symbol": "3533",
      "name": "Lotes Co., Ltd.",
      "price": 2020.0,
      "prev_close": 2015.0,
      "change": 5.0,
      "change_pct": 0.25,
      "currency": "TWD",
      "market": "TW",
      "updated_at": "2026-07-16T20:14:20.637060Z"
    },
    {
      "symbol": "4904",
      "name": "Far EasTone Telecomm",
      "price": 101.0,
      "prev_close": 96.3,
      "change": 4.7,
      "change_pct": 4.88,
      "currency": "TWD",
      "market": "TW",
      "updated_at": "2026-07-16T20:14:20.966932Z"
    },
    {
      "symbol": "5871",
      "name": "Chailease Holding Co",
      "price": 120.5,
      "prev_close": 118.5,
      "change": 2.0,
      "change_pct": 1.69,
      "currency": "TWD",
      "market": "TW",
      "updated_at": "2026-07-16T20:14:22.341386Z"
    },
    {
      "symbol": "6505",
      "name": "Formosa Petrochemica",
      "price": 80.0,
      "prev_close": 72.8,
      "change": 7.2,
      "change_pct": 9.89,
      "currency": "TWD",
      "market": "TW",
      "updated_at": "2026-07-16T20:14:22.779736Z"
    },
    {
      "symbol": "6669",
      "name": "Wiwynn Corporation",
      "price": 5115.0,
      "prev_close": 5125.0,
      "change": -10.0,
      "change_pct": -0.2,
      "currency": "TWD",
      "market": "TW",
      "updated_at": "2026-07-16T20:14:23.114520Z"
    },
    {
      "symbol": "6770",
      "name": "Powerchip Semiconduc",
      "price": 76.5,
      "prev_close": 76.1,
      "change": 0.4,
      "change_pct": 0.53,
      "currency": "TWD",
      "market": "TW",
      "updated_at": "2026-07-16T20:14:23.493662Z"
    },
    {
      "symbol": "8046",
      "name": "Nan Ya Printed Circu",
      "price": 1275.0,
      "prev_close": 1415.0,
      "change": -140.0,
      "change_pct": -9.89,
      "currency": "TWD",
      "market": "TW",
      "updated_at": "2026-07-16T20:14:23.929075Z"
    },
    {
      "symbol": "9910",
      "name": "Feng Tay Enterprises",
      "price": 67.8,
      "prev_close": 67.4,
      "change": 0.4,
      "change_pct": 0.59,
      "currency": "TWD",
      "market": "TW",
      "updated_at": "2026-07-16T20:14:24.367960Z"
    },
    {
      "symbol": "2105",
      "name": "Cheng Shin Rubber In",
      "price": 33.55,
      "prev_close": 32.85,
      "change": 0.7,
      "change_pct": 2.13,
      "currency": "TWD",
      "market": "TW",
      "updated_at": "2026-07-16T20:14:24.792710Z"
    },
    {
      "symbol": "2049",
      "name": "Hiwin Technologies C",
      "price": 332.0,
      "prev_close": 322.0,
      "change": 10.0,
      "change_pct": 3.11,
      "currency": "TWD",
      "market": "TW",
      "updated_at": "2026-07-16T20:14:25.159462Z"
    },
    {
      "symbol": "2915",
      "name": "Ruentex Industries L",
      "price": 52.8,
      "prev_close": 52.4,
      "change": 0.4,
      "change_pct": 0.76,
      "currency": "TWD",
      "market": "TW",
      "updated_at": "2026-07-16T20:14:25.630012Z"
    },
    {
      "symbol": "1216",
      "name": "Uni-President Enterp",
      "price": 79.0,
      "prev_close": 78.3,
      "change": 0.7,
      "change_pct": 0.89,
      "currency": "TWD",
      "market": "TW",
      "updated_at": "2026-07-16T20:14:25.981435Z"
    },
    {
      "symbol": "2801",
      "name": "Chang Hwa Commercial",
      "price": 23.95,
      "prev_close": 23.85,
      "change": 0.1,
      "change_pct": 0.42,
      "currency": "TWD",
      "market": "TW",
      "updated_at": "2026-07-16T20:14:27.486385Z"
    },
    {
      "symbol": "1402",
      "name": "Far Eastern New Cent",
      "price": 27.8,
      "prev_close": 27.6,
      "change": 0.2,
      "change_pct": 0.72,
      "currency": "TWD",
      "market": "TW",
      "updated_at": "2026-07-16T20:14:27.911604Z"
    },
    {
      "symbol": "1101",
      "name": "TCC Group Holdings C",
      "price": 23.95,
      "prev_close": 23.55,
      "change": 0.4,
      "change_pct": 1.7,
      "currency": "TWD",
      "market": "TW",
      "updated_at": "2026-07-16T20:14:28.322095Z"
    },
    {
      "symbol": "1102",
      "name": "Asia Cement Corporat",
      "price": 33.0,
      "prev_close": 34.75,
      "change": -1.75,
      "change_pct": -5.04,
      "currency": "TWD",
      "market": "TW",
      "updated_at": "2026-07-16T20:14:28.769488Z"
    },
    {
      "symbol": "2912",
      "name": "President Chain Stor",
      "price": 245.5,
      "prev_close": 244.0,
      "change": 1.5,
      "change_pct": 0.61,
      "currency": "TWD",
      "market": "TW",
      "updated_at": "2026-07-16T20:14:29.188264Z"
    },
    {
      "symbol": "2880",
      "name": "Hua Nan Financial Ho",
      "price": 39.4,
      "prev_close": 39.0,
      "change": 0.4,
      "change_pct": 1.03,
      "currency": "TWD",
      "market": "TW",
      "updated_at": "2026-07-16T20:14:30.238095Z"
    },
    {
      "symbol": "5880",
      "name": "Taiwan Cooperative F",
      "price": 25.5,
      "prev_close": 25.25,
      "change": 0.25,
      "change_pct": 0.99,
      "currency": "TWD",
      "market": "TW",
      "updated_at": "2026-07-16T20:14:30.784755Z"
    },
    {
      "symbol": "2474",
      "name": "Catcher Technology C",
      "price": 189.0,
      "prev_close": 191.5,
      "change": -2.5,
      "change_pct": -1.31,
      "currency": "TWD",
      "market": "TW",
      "updated_at": "2026-07-16T20:14:31.190481Z"
    },
    {
      "symbol": "2352",
      "name": "Qisda Corporation",
      "price": 31.35,
      "prev_close": 31.4,
      "change": -0.05,
      "change_pct": -0.16,
      "currency": "TWD",
      "market": "TW",
      "updated_at": "2026-07-16T20:14:31.600823Z"
    },
    {
      "symbol": "2301",
      "name": "Lite-On Technology C",
      "price": 218.0,
      "prev_close": 216.0,
      "change": 2.0,
      "change_pct": 0.93,
      "currency": "TWD",
      "market": "TW",
      "updated_at": "2026-07-16T20:14:32.983254Z"
    },
    {
      "symbol": "2356",
      "name": "Inventec Corporation",
      "price": 60.7,
      "prev_close": 61.1,
      "change": -0.4,
      "change_pct": -0.65,
      "currency": "TWD",
      "market": "TW",
      "updated_at": "2026-07-16T20:14:33.370682Z"
    },
    {
      "symbol": "2324",
      "name": "Compal Electronics, ",
      "price": 35.95,
      "prev_close": 36.15,
      "change": -0.2,
      "change_pct": -0.55,
      "currency": "TWD",
      "market": "TW",
      "updated_at": "2026-07-16T20:14:33.828109Z"
    },
    {
      "symbol": "2353",
      "name": "Acer Incorporated",
      "price": 30.75,
      "prev_close": 31.15,
      "change": -0.4,
      "change_pct": -1.28,
      "currency": "TWD",
      "market": "TW",
      "updated_at": "2026-07-16T20:14:34.264145Z"
    },
    {
      "symbol": "2360",
      "name": "Chroma ATE Inc.",
      "price": 1990.0,
      "prev_close": 1905.0,
      "change": 85.0,
      "change_pct": 4.46,
      "currency": "TWD",
      "market": "TW",
      "updated_at": "2026-07-16T20:14:34.639986Z"
    },
    {
      "symbol": "2347",
      "name": "Synnex Technology In",
      "price": 87.3,
      "prev_close": 87.1,
      "change": 0.2,
      "change_pct": 0.23,
      "currency": "TWD",
      "market": "TW",
      "updated_at": "2026-07-16T20:14:35.148744Z"
    },
    {
      "symbol": "2385",
      "name": "Chicony Electronics ",
      "price": 105.5,
      "prev_close": 105.5,
      "change": 0.0,
      "change_pct": 0.0,
      "currency": "TWD",
      "market": "TW",
      "updated_at": "2026-07-16T20:14:35.579673Z"
    },
    {
      "symbol": "3006",
      "name": "Elite Semiconductor ",
      "price": 220.0,
      "prev_close": 239.0,
      "change": -19.0,
      "change_pct": -7.95,
      "currency": "TWD",
      "market": "TW",
      "updated_at": "2026-07-16T20:14:35.942687Z"
    },
    {
      "symbol": "4958",
      "name": "Zhen Ding Technology",
      "price": 578.0,
      "prev_close": 620.0,
      "change": -42.0,
      "change_pct": -6.77,
      "currency": "TWD",
      "market": "TW",
      "updated_at": "2026-07-16T20:14:36.735557Z"
    },
    {
      "symbol": "6176",
      "name": "Radiant Opto-Electro",
      "price": 88.6,
      "prev_close": 88.3,
      "change": 0.3,
      "change_pct": 0.34,
      "currency": "TWD",
      "market": "TW",
      "updated_at": "2026-07-16T20:14:38.500692Z"
    },
    {
      "symbol": "6153",
      "name": "Career Technology (M",
      "price": 18.2,
      "prev_close": 18.8,
      "change": -0.6,
      "change_pct": -3.19,
      "currency": "TWD",
      "market": "TW",
      "updated_at": "2026-07-16T20:14:38.824509Z"
    },
    {
      "symbol": "6202",
      "name": "Holtek Semiconductor",
      "price": 64.1,
      "prev_close": 70.8,
      "change": -6.7,
      "change_pct": -9.46,
      "currency": "TWD",
      "market": "TW",
      "updated_at": "2026-07-16T20:14:39.209915Z"
    },
    {
      "symbol": "6239",
      "name": "Powertech Technology",
      "price": 316.5,
      "prev_close": 314.5,
      "change": 2.0,
      "change_pct": 0.64,
      "currency": "TWD",
      "market": "TW",
      "updated_at": "2026-07-16T20:14:39.556675Z"
    },
    {
      "symbol": "6415",
      "name": "Silergy Corp.",
      "price": 473.0,
      "prev_close": 503.0,
      "change": -30.0,
      "change_pct": -5.96,
      "currency": "TWD",
      "market": "TW",
      "updated_at": "2026-07-16T20:14:40.016140Z"
    },
    {
      "symbol": "6451",
      "name": "ShunSin Technology H",
      "price": 477.0,
      "prev_close": 491.0,
      "change": -14.0,
      "change_pct": -2.85,
      "currency": "TWD",
      "market": "TW",
      "updated_at": "2026-07-16T20:14:40.386353Z"
    },
    {
      "symbol": "6657",
      "name": "Energenesis Biomedic",
      "price": 35.95,
      "prev_close": 34.75,
      "change": 1.2,
      "change_pct": 3.45,
      "currency": "TWD",
      "market": "TW",
      "updated_at": "2026-07-16T20:14:41.537433Z"
    },
    {
      "symbol": "2609",
      "name": "Yang Ming Marine Tra",
      "price": 50.2,
      "prev_close": 50.1,
      "change": 0.1,
      "change_pct": 0.2,
      "currency": "TWD",
      "market": "TW",
      "updated_at": "2026-07-16T20:14:42.918243Z"
    },
    {
      "symbol": "2615",
      "name": "Wan Hai Lines Ltd.",
      "price": 80.7,
      "prev_close": 81.4,
      "change": -0.7,
      "change_pct": -0.86,
      "currency": "TWD",
      "market": "TW",
      "updated_at": "2026-07-16T20:14:43.580812Z"
    },
    {
      "symbol": "2618",
      "name": "EVA Airways Corp.",
      "price": 41.9,
      "prev_close": 42.05,
      "change": -0.15,
      "change_pct": -0.36,
      "currency": "TWD",
      "market": "TW",
      "updated_at": "2026-07-16T20:14:43.968013Z"
    },
    {
      "symbol": "2603",
      "name": "Evergreen Marine Cor",
      "price": 200.0,
      "prev_close": 198.5,
      "change": 1.5,
      "change_pct": 0.76,
      "currency": "TWD",
      "market": "TW",
      "updated_at": "2026-07-16T20:14:44.357612Z"
    },
    {
      "symbol": "2605",
      "name": "Sincere Navigation C",
      "price": 31.25,
      "prev_close": 31.6,
      "change": -0.35,
      "change_pct": -1.11,
      "currency": "TWD",
      "market": "TW",
      "updated_at": "2026-07-16T20:14:44.850634Z"
    },
    {
      "symbol": "2606",
      "name": "U-Ming Marine Transp",
      "price": 63.6,
      "prev_close": 64.2,
      "change": -0.6,
      "change_pct": -0.93,
      "currency": "TWD",
      "market": "TW",
      "updated_at": "2026-07-16T20:14:45.239944Z"
    },
    {
      "symbol": "2610",
      "name": "CHINA AIR LINES",
      "price": 20.9,
      "prev_close": 21.25,
      "change": -0.35,
      "change_pct": -1.65,
      "currency": "TWD",
      "market": "TW",
      "updated_at": "2026-07-16T20:14:45.642750Z"
    },
    {
      "symbol": "1904",
      "name": "Cheng Loong Corporat",
      "price": 22.4,
      "prev_close": 22.45,
      "change": -0.05,
      "change_pct": -0.22,
      "currency": "TWD",
      "market": "TW",
      "updated_at": "2026-07-16T20:14:46.494132Z"
    },
    {
      "symbol": "1907",
      "name": "YFY Inc.",
      "price": 28.4,
      "prev_close": 29.2,
      "change": -0.8,
      "change_pct": -2.74,
      "currency": "TWD",
      "market": "TW",
      "updated_at": "2026-07-16T20:14:46.908762Z"
    },
    {
      "symbol": "2101",
      "name": "Nankang Rubber Tire ",
      "price": 34.55,
      "prev_close": 34.1,
      "change": 0.45,
      "change_pct": 1.32,
      "currency": "TWD",
      "market": "TW",
      "updated_at": "2026-07-16T20:14:48.280030Z"
    },
    {
      "symbol": "2103",
      "name": "TSRC Corporation",
      "price": 24.55,
      "prev_close": 25.6,
      "change": -1.05,
      "change_pct": -4.1,
      "currency": "TWD",
      "market": "TW",
      "updated_at": "2026-07-16T20:14:48.685326Z"
    },
    {
      "symbol": "1590",
      "name": "Airtac International",
      "price": 1350.0,
      "prev_close": 1365.0,
      "change": -15.0,
      "change_pct": -1.1,
      "currency": "TWD",
      "market": "TW",
      "updated_at": "2026-07-16T20:14:49.047072Z"
    },
    {
      "symbol": "6271",
      "name": "Tong Hsing Electroni",
      "price": 224.0,
      "prev_close": 223.5,
      "change": 0.5,
      "change_pct": 0.22,
      "currency": "TWD",
      "market": "TW",
      "updated_at": "2026-07-16T20:14:49.928344Z"
    },
    {
      "symbol": "6278",
      "name": "Taiwan Surface Mount",
      "price": 177.5,
      "prev_close": 177.0,
      "change": 0.5,
      "change_pct": 0.28,
      "currency": "TWD",
      "market": "TW",
      "updated_at": "2026-07-16T20:14:50.365507Z"
    }
  ],
  "us_count": 96,
  "tw_count": 88,
  "updated_at": "2026-07-16T20:14:51.779478Z"
}