{
  "us_stocks": [
    {
      "symbol": "AAPL",
      "name": "Apple Inc.",
      "price": 326.59,
      "prev_close": 333.66,
      "change": -7.07,
      "change_pct": -2.12,
      "currency": "USD",
      "market": "US",
      "updated_at": "2026-07-20T21:34:23.740952Z"
    },
    {
      "symbol": "MSFT",
      "name": "Microsoft Corporation",
      "price": 402.29,
      "prev_close": 393.51,
      "change": 8.78,
      "change_pct": 2.23,
      "currency": "USD",
      "market": "US",
      "updated_at": "2026-07-20T21:34:24.666640Z"
    },
    {
      "symbol": "NVDA",
      "name": "NVIDIA Corporation",
      "price": 203.28,
      "prev_close": 202.49,
      "change": 0.79,
      "change_pct": 0.39,
      "currency": "USD",
      "market": "US",
      "updated_at": "2026-07-20T21:34:25.619023Z"
    },
    {
      "symbol": "GOOGL",
      "name": "Alphabet Inc.",
      "price": 351.99,
      "prev_close": 346.4,
      "change": 5.59,
      "change_pct": 1.61,
      "currency": "USD",
      "market": "US",
      "updated_at": "2026-07-20T21:34:26.555881Z"
    },
    {
      "symbol": "AMZN",
      "name": "Amazon.com, Inc.",
      "price": 249.99,
      "prev_close": 246.71,
      "change": 3.28,
      "change_pct": 1.33,
      "currency": "USD",
      "market": "US",
      "updated_at": "2026-07-20T21:34:27.448728Z"
    },
    {
      "symbol": "META",
      "name": "Meta Platforms, Inc.",
      "price": 645.85,
      "prev_close": 640.21,
      "change": 5.64,
      "change_pct": 0.88,
      "currency": "USD",
      "market": "US",
      "updated_at": "2026-07-20T21:34:30.207471Z"
    },
    {
      "symbol": "TSLA",
      "name": "Tesla, Inc.",
      "price": 369.57,
      "prev_close": 380.03,
      "change": -10.46,
      "change_pct": -2.75,
      "currency": "USD",
      "market": "US",
      "updated_at": "2026-07-20T21:34:31.433542Z"
    },
    {
      "symbol": "AVGO",
      "name": "Broadcom Inc.",
      "price": 378.16,
      "prev_close": 370.0,
      "change": 8.16,
      "change_pct": 2.21,
      "currency": "USD",
      "market": "US",
      "updated_at": "2026-07-20T21:34:32.464755Z"
    },
    {
      "symbol": "ORCL",
      "name": "Oracle Corporation",
      "price": 121.38,
      "prev_close": 126.54,
      "change": -5.16,
      "change_pct": -4.08,
      "currency": "USD",
      "market": "US",
      "updated_at": "2026-07-20T21:34:33.320499Z"
    },
    {
      "symbol": "NFLX",
      "name": "Netflix, Inc.",
      "price": 67.6,
      "prev_close": 69.14,
      "change": -1.54,
      "change_pct": -2.23,
      "currency": "USD",
      "market": "US",
      "updated_at": "2026-07-20T21:34:34.336081Z"
    },
    {
      "symbol": "AMD",
      "name": "Advanced Micro Devices, Inc.",
      "price": 503.57,
      "prev_close": 492.5,
      "change": 11.07,
      "change_pct": 2.25,
      "currency": "USD",
      "market": "US",
      "updated_at": "2026-07-20T21:34:35.286686Z"
    },
    {
      "symbol": "ADBE",
      "name": "Adobe Inc.",
      "price": 234.74,
      "prev_close": 237.5,
      "change": -2.76,
      "change_pct": -1.16,
      "currency": "USD",
      "market": "US",
      "updated_at": "2026-07-20T21:34:39.211274Z"
    },
    {
      "symbol": "CRM",
      "name": "Salesforce, Inc.",
      "price": 173.79,
      "prev_close": 170.34,
      "change": 3.45,
      "change_pct": 2.03,
      "currency": "USD",
      "market": "US",
      "updated_at": "2026-07-20T21:34:39.988493Z"
    },
    {
      "symbol": "INTC",
      "name": "Intel Corporation",
      "price": 97.06,
      "prev_close": 93.97,
      "change": 3.09,
      "change_pct": 3.29,
      "currency": "USD",
      "market": "US",
      "updated_at": "2026-07-20T21:34:42.767871Z"
    },
    {
      "symbol": "QCOM",
      "name": "QUALCOMM Incorporated",
      "price": 170.32,
      "prev_close": 171.45,
      "change": -1.13,
      "change_pct": -0.66,
      "currency": "USD",
      "market": "US",
      "updated_at": "2026-07-20T21:34:43.815982Z"
    },
    {
      "symbol": "TXN",
      "name": "Texas Instruments Incorporated",
      "price": 284.07,
      "prev_close": 283.67,
      "change": 0.4,
      "change_pct": 0.14,
      "currency": "USD",
      "market": "US",
      "updated_at": "2026-07-20T21:34:44.796051Z"
    },
    {
      "symbol": "AMAT",
      "name": "Applied Materials, Inc.",
      "price": 525.7,
      "prev_close": 522.24,
      "change": 3.46,
      "change_pct": 0.66,
      "currency": "USD",
      "market": "US",
      "updated_at": "2026-07-20T21:34:45.937541Z"
    },
    {
      "symbol": "MU",
      "name": "Micron Technology, Inc.",
      "price": 865.46,
      "prev_close": 844.0,
      "change": 21.46,
      "change_pct": 2.54,
      "currency": "USD",
      "market": "US",
      "updated_at": "2026-07-20T21:34:47.016915Z"
    },
    {
      "symbol": "KLAC",
      "name": "KLA Corporation",
      "price": 207.6,
      "prev_close": 212.41,
      "change": -4.81,
      "change_pct": -2.26,
      "currency": "USD",
      "market": "US",
      "updated_at": "2026-07-20T21:34:47.917691Z"
    },
    {
      "symbol": "LRCX",
      "name": "Lam Research Corporation",
      "price": 306.76,
      "prev_close": 310.06,
      "change": -3.3,
      "change_pct": -1.06,
      "currency": "USD",
      "market": "US",
      "updated_at": "2026-07-20T21:34:48.959844Z"
    },
    {
      "symbol": "BRK-B",
      "name": "Berkshire Hathaway Inc.",
      "price": 491.25,
      "prev_close": 491.15,
      "change": 0.1,
      "change_pct": 0.02,
      "currency": "USD",
      "market": "US",
      "updated_at": "2026-07-20T21:34:50.961449Z"
    },
    {
      "symbol": "JPM",
      "name": "JP Morgan Chase & Co.",
      "price": 338.87,
      "prev_close": 342.38,
      "change": -3.51,
      "change_pct": -1.03,
      "currency": "USD",
      "market": "US",
      "updated_at": "2026-07-20T21:34:52.738239Z"
    },
    {
      "symbol": "V",
      "name": "Visa Inc.",
      "price": 360.57,
      "prev_close": 358.6,
      "change": 1.97,
      "change_pct": 0.55,
      "currency": "USD",
      "market": "US",
      "updated_at": "2026-07-20T21:34:53.785580Z"
    },
    {
      "symbol": "MA",
      "name": "Mastercard Incorporated",
      "price": 547.44,
      "prev_close": 544.46,
      "change": 2.98,
      "change_pct": 0.55,
      "currency": "USD",
      "market": "US",
      "updated_at": "2026-07-20T21:34:54.636745Z"
    },
    {
      "symbol": "BAC",
      "name": "Bank of America Corporation",
      "price": 60.42,
      "prev_close": 61.28,
      "change": -0.86,
      "change_pct": -1.4,
      "currency": "USD",
      "market": "US",
      "updated_at": "2026-07-20T21:34:56.054776Z"
    },
    {
      "symbol": "GS",
      "name": "Goldman Sachs Group, Inc. (The)",
      "price": 1055.03,
      "prev_close": 1067.05,
      "change": -12.02,
      "change_pct": -1.13,
      "currency": "USD",
      "market": "US",
      "updated_at": "2026-07-20T21:34:57.063561Z"
    },
    {
      "symbol": "MS",
      "name": "Morgan Stanley",
      "price": 210.94,
      "prev_close": 215.5,
      "change": -4.56,
      "change_pct": -2.12,
      "currency": "USD",
      "market": "US",
      "updated_at": "2026-07-20T21:34:58.087488Z"
    },
    {
      "symbol": "WFC",
      "name": "Wells Fargo & Company",
      "price": 86.33,
      "prev_close": 87.61,
      "change": -1.28,
      "change_pct": -1.46,
      "currency": "USD",
      "market": "US",
      "updated_at": "2026-07-20T21:34:59.220435Z"
    },
    {
      "symbol": "AXP",
      "name": "American Express Company",
      "price": 351.93,
      "prev_close": 354.16,
      "change": -2.23,
      "change_pct": -0.63,
      "currency": "USD",
      "market": "US",
      "updated_at": "2026-07-20T21:35:00.748008Z"
    },
    {
      "symbol": "BLK",
      "name": "BlackRock, Inc.",
      "price": 1054.11,
      "prev_close": 1079.74,
      "change": -25.63,
      "change_pct": -2.37,
      "currency": "USD",
      "market": "US",
      "updated_at": "2026-07-20T21:35:01.911726Z"
    },
    {
      "symbol": "SCHW",
      "name": "The Charles Schwab Corporation",
      "price": 102.54,
      "prev_close": 101.68,
      "change": 0.86,
      "change_pct": 0.85,
      "currency": "USD",
      "market": "US",
      "updated_at": "2026-07-20T21:35:04.817085Z"
    },
    {
      "symbol": "C",
      "name": "Citigroup Inc.",
      "price": 128.72,
      "prev_close": 129.59,
      "change": -0.87,
      "change_pct": -0.67,
      "currency": "USD",
      "market": "US",
      "updated_at": "2026-07-20T21:35:05.765098Z"
    },
    {
      "symbol": "SPGI",
      "name": "S&P Global Inc.",
      "price": 448.35,
      "prev_close": 451.0,
      "change": -2.65,
      "change_pct": -0.59,
      "currency": "USD",
      "market": "US",
      "updated_at": "2026-07-20T21:35:06.743984Z"
    },
    {
      "symbol": "MCO",
      "name": "Moody's Corporation",
      "price": 505.37,
      "prev_close": 511.09,
      "change": -5.72,
      "change_pct": -1.12,
      "currency": "USD",
      "market": "US",
      "updated_at": "2026-07-20T21:35:08.169804Z"
    },
    {
      "symbol": "COF",
      "name": "Capital One Financial Corporation",
      "price": 206.77,
      "prev_close": 208.03,
      "change": -1.26,
      "change_pct": -0.61,
      "currency": "USD",
      "market": "US",
      "updated_at": "2026-07-20T21:35:09.170859Z"
    },
    {
      "symbol": "LLY",
      "name": "Eli Lilly and Company",
      "price": 1146.9,
      "prev_close": 1176.53,
      "change": -29.63,
      "change_pct": -2.52,
      "currency": "USD",
      "market": "US",
      "updated_at": "2026-07-20T21:35:10.102133Z"
    },
    {
      "symbol": "UNH",
      "name": "UnitedHealth Group Incorporated",
      "price": 421.55,
      "prev_close": 427.0,
      "change": -5.45,
      "change_pct": -1.28,
      "currency": "USD",
      "market": "US",
      "updated_at": "2026-07-20T21:35:11.085036Z"
    },
    {
      "symbol": "JNJ",
      "name": "Johnson & Johnson",
      "price": 248.82,
      "prev_close": 253.48,
      "change": -4.66,
      "change_pct": -1.84,
      "currency": "USD",
      "market": "US",
      "updated_at": "2026-07-20T21:35:12.151405Z"
    },
    {
      "symbol": "ABBV",
      "name": "AbbVie Inc.",
      "price": 253.38,
      "prev_close": 254.25,
      "change": -0.87,
      "change_pct": -0.34,
      "currency": "USD",
      "market": "US",
      "updated_at": "2026-07-20T21:35:12.939005Z"
    },
    {
      "symbol": "MRK",
      "name": "Merck & Co., Inc.",
      "price": 124.4,
      "prev_close": 127.51,
      "change": -3.11,
      "change_pct": -2.44,
      "currency": "USD",
      "market": "US",
      "updated_at": "2026-07-20T21:35:13.884434Z"
    },
    {
      "symbol": "TMO",
      "name": "Thermo Fisher Scientific Inc.",
      "price": 526.23,
      "prev_close": 533.0,
      "change": -6.77,
      "change_pct": -1.27,
      "currency": "USD",
      "market": "US",
      "updated_at": "2026-07-20T21:35:15.723162Z"
    },
    {
      "symbol": "ABT",
      "name": "Abbott Laboratories",
      "price": 101.66,
      "prev_close": 100.99,
      "change": 0.67,
      "change_pct": 0.66,
      "currency": "USD",
      "market": "US",
      "updated_at": "2026-07-20T21:35:16.643479Z"
    },
    {
      "symbol": "DHR",
      "name": "Danaher Corporation",
      "price": 201.11,
      "prev_close": 203.83,
      "change": -2.72,
      "change_pct": -1.33,
      "currency": "USD",
      "market": "US",
      "updated_at": "2026-07-20T21:35:17.759809Z"
    },
    {
      "symbol": "AMGN",
      "name": "Amgen Inc.",
      "price": 364.17,
      "prev_close": 365.0,
      "change": -0.83,
      "change_pct": -0.23,
      "currency": "USD",
      "market": "US",
      "updated_at": "2026-07-20T21:35:18.903648Z"
    },
    {
      "symbol": "ISRG",
      "name": "Intuitive Surgical, Inc.",
      "price": 353.17,
      "prev_close": 345.58,
      "change": 7.59,
      "change_pct": 2.2,
      "currency": "USD",
      "market": "US",
      "updated_at": "2026-07-20T21:35:19.823711Z"
    },
    {
      "symbol": "GILD",
      "name": "Gilead Sciences, Inc.",
      "price": 133.21,
      "prev_close": 134.3,
      "change": -1.09,
      "change_pct": -0.81,
      "currency": "USD",
      "market": "US",
      "updated_at": "2026-07-20T21:35:20.943089Z"
    },
    {
      "symbol": "VRTX",
      "name": "Vertex Pharmaceuticals Incorporated",
      "price": 480.5,
      "prev_close": 485.88,
      "change": -5.38,
      "change_pct": -1.11,
      "currency": "USD",
      "market": "US",
      "updated_at": "2026-07-20T21:35:21.856166Z"
    },
    {
      "symbol": "REGN",
      "name": "Regeneron Pharmaceuticals, Inc.",
      "price": 672.15,
      "prev_close": 674.0,
      "change": -1.85,
      "change_pct": -0.27,
      "currency": "USD",
      "market": "US",
      "updated_at": "2026-07-20T21:35:22.948144Z"
    },
    {
      "symbol": "BSX",
      "name": "Boston Scientific Corporation",
      "price": 43.77,
      "prev_close": 44.1,
      "change": -0.33,
      "change_pct": -0.75,
      "currency": "USD",
      "market": "US",
      "updated_at": "2026-07-20T21:35:23.891642Z"
    },
    {
      "symbol": "SYK",
      "name": "Stryker Corporation",
      "price": 319.14,
      "prev_close": 322.75,
      "change": -3.61,
      "change_pct": -1.12,
      "currency": "USD",
      "market": "US",
      "updated_at": "2026-07-20T21:35:25.007848Z"
    },
    {
      "symbol": "COST",
      "name": "Costco Wholesale Corporation",
      "price": 935.8,
      "prev_close": 940.23,
      "change": -4.43,
      "change_pct": -0.47,
      "currency": "USD",
      "market": "US",
      "updated_at": "2026-07-20T21:35:26.146692Z"
    },
    {
      "symbol": "WMT",
      "name": "Walmart Inc.",
      "price": 112.2,
      "prev_close": 114.3,
      "change": -2.1,
      "change_pct": -1.84,
      "currency": "USD",
      "market": "US",
      "updated_at": "2026-07-20T21:35:27.534260Z"
    },
    {
      "symbol": "HD",
      "name": "The Home Depot, Inc.",
      "price": 333.04,
      "prev_close": 339.49,
      "change": -6.45,
      "change_pct": -1.9,
      "currency": "USD",
      "market": "US",
      "updated_at": "2026-07-20T21:35:28.678934Z"
    },
    {
      "symbol": "MCD",
      "name": "McDonald's Corporation",
      "price": 267.64,
      "prev_close": 267.75,
      "change": -0.11,
      "change_pct": -0.04,
      "currency": "USD",
      "market": "US",
      "updated_at": "2026-07-20T21:35:29.789091Z"
    },
    {
      "symbol": "SBUX",
      "name": "Starbucks Corporation",
      "price": 104.81,
      "prev_close": 105.55,
      "change": -0.74,
      "change_pct": -0.7,
      "currency": "USD",
      "market": "US",
      "updated_at": "2026-07-20T21:35:30.854934Z"
    },
    {
      "symbol": "NKE",
      "name": "NIKE, Inc.",
      "price": 43.47,
      "prev_close": 43.79,
      "change": -0.32,
      "change_pct": -0.73,
      "currency": "USD",
      "market": "US",
      "updated_at": "2026-07-20T21:35:31.728159Z"
    },
    {
      "symbol": "LOW",
      "name": "Lowe's Companies, Inc.",
      "price": 204.71,
      "prev_close": 209.41,
      "change": -4.7,
      "change_pct": -2.24,
      "currency": "USD",
      "market": "US",
      "updated_at": "2026-07-20T21:35:32.773322Z"
    },
    {
      "symbol": "TGT",
      "name": "Target Corporation",
      "price": 139.59,
      "prev_close": 139.69,
      "change": -0.1,
      "change_pct": -0.07,
      "currency": "USD",
      "market": "US",
      "updated_at": "2026-07-20T21:35:34.087046Z"
    },
    {
      "symbol": "BKNG",
      "name": "Booking Holdings Inc.",
      "price": 179.45,
      "prev_close": 181.7,
      "change": -2.25,
      "change_pct": -1.24,
      "currency": "USD",
      "market": "US",
      "updated_at": "2026-07-20T21:35:34.938736Z"
    },
    {
      "symbol": "MAR",
      "name": "Marriott International",
      "price": 366.93,
      "prev_close": 366.16,
      "change": 0.77,
      "change_pct": 0.21,
      "currency": "USD",
      "market": "US",
      "updated_at": "2026-07-20T21:35:36.018703Z"
    },
    {
      "symbol": "HLT",
      "name": "Hilton Worldwide Holdings Inc.",
      "price": 323.43,
      "prev_close": 321.3,
      "change": 2.13,
      "change_pct": 0.66,
      "currency": "USD",
      "market": "US",
      "updated_at": "2026-07-20T21:35:37.909859Z"
    },
    {
      "symbol": "XOM",
      "name": "ExxonMobil Holdings Corporation",
      "price": 148.36,
      "prev_close": 147.9,
      "change": 0.46,
      "change_pct": 0.31,
      "currency": "USD",
      "market": "US",
      "updated_at": "2026-07-20T21:35:38.851589Z"
    },
    {
      "symbol": "CVX",
      "name": "Chevron Corporation",
      "price": 189.71,
      "prev_close": 187.91,
      "change": 1.8,
      "change_pct": 0.96,
      "currency": "USD",
      "market": "US",
      "updated_at": "2026-07-20T21:35:39.789937Z"
    },
    {
      "symbol": "CAT",
      "name": "Caterpillar Inc.",
      "price": 864.3,
      "prev_close": 879.33,
      "change": -15.03,
      "change_pct": -1.71,
      "currency": "USD",
      "market": "US",
      "updated_at": "2026-07-20T21:35:40.810467Z"
    },
    {
      "symbol": "GE",
      "name": "GE Aerospace",
      "price": 341.3,
      "prev_close": 349.28,
      "change": -7.98,
      "change_pct": -2.28,
      "currency": "USD",
      "market": "US",
      "updated_at": "2026-07-20T21:35:41.810689Z"
    },
    {
      "symbol": "BA",
      "name": "The Boeing Company",
      "price": 209.48,
      "prev_close": 214.25,
      "change": -4.77,
      "change_pct": -2.23,
      "currency": "USD",
      "market": "US",
      "updated_at": "2026-07-20T21:35:42.831500Z"
    },
    {
      "symbol": "RTX",
      "name": "RTX Corporation",
      "price": 194.44,
      "prev_close": 193.6,
      "change": 0.84,
      "change_pct": 0.43,
      "currency": "USD",
      "market": "US",
      "updated_at": "2026-07-20T21:35:43.898942Z"
    },
    {
      "symbol": "HON",
      "name": "Honeywell International Inc.",
      "price": 226.18,
      "prev_close": 220.39,
      "change": 5.79,
      "change_pct": 2.63,
      "currency": "USD",
      "market": "US",
      "updated_at": "2026-07-20T21:35:45.097874Z"
    },
    {
      "symbol": "UPS",
      "name": "United Parcel Service, Inc.",
      "price": 113.15,
      "prev_close": 117.26,
      "change": -4.11,
      "change_pct": -3.51,
      "currency": "USD",
      "market": "US",
      "updated_at": "2026-07-20T21:35:46.239154Z"
    },
    {
      "symbol": "LMT",
      "name": "Lockheed Martin Corporation",
      "price": 509.54,
      "prev_close": 509.4,
      "change": 0.14,
      "change_pct": 0.03,
      "currency": "USD",
      "market": "US",
      "updated_at": "2026-07-20T21:35:47.169277Z"
    },
    {
      "symbol": "DE",
      "name": "Deere & Company",
      "price": 586.0,
      "prev_close": 597.74,
      "change": -11.74,
      "change_pct": -1.96,
      "currency": "USD",
      "market": "US",
      "updated_at": "2026-07-20T21:35:48.496857Z"
    },
    {
      "symbol": "DIS",
      "name": "The Walt Disney Company",
      "price": 96.41,
      "prev_close": 97.67,
      "change": -1.26,
      "change_pct": -1.29,
      "currency": "USD",
      "market": "US",
      "updated_at": "2026-07-20T21:35:49.348663Z"
    },
    {
      "symbol": "CMCSA",
      "name": "Comcast Corporation",
      "price": 23.78,
      "prev_close": 23.86,
      "change": -0.08,
      "change_pct": -0.34,
      "currency": "USD",
      "market": "US",
      "updated_at": "2026-07-20T21:35:50.263421Z"
    },
    {
      "symbol": "T",
      "name": "AT&T Inc.",
      "price": 21.95,
      "prev_close": 21.84,
      "change": 0.11,
      "change_pct": 0.5,
      "currency": "USD",
      "market": "US",
      "updated_at": "2026-07-20T21:35:51.341710Z"
    },
    {
      "symbol": "VZ",
      "name": "Verizon Communications Inc.",
      "price": 43.5,
      "prev_close": 43.69,
      "change": -0.19,
      "change_pct": -0.43,
      "currency": "USD",
      "market": "US",
      "updated_at": "2026-07-20T21:35:52.619856Z"
    },
    {
      "symbol": "TMUS",
      "name": "T-Mobile US, Inc.",
      "price": 195.64,
      "prev_close": 192.73,
      "change": 2.91,
      "change_pct": 1.51,
      "currency": "USD",
      "market": "US",
      "updated_at": "2026-07-20T21:35:53.747143Z"
    },
    {
      "symbol": "PYPL",
      "name": "PayPal Holdings, Inc.",
      "price": 56.82,
      "prev_close": 56.38,
      "change": 0.44,
      "change_pct": 0.78,
      "currency": "USD",
      "market": "US",
      "updated_at": "2026-07-20T21:35:54.615773Z"
    },
    {
      "symbol": "UBER",
      "name": "Uber Technologies, Inc.",
      "price": 72.17,
      "prev_close": 72.37,
      "change": -0.2,
      "change_pct": -0.28,
      "currency": "USD",
      "market": "US",
      "updated_at": "2026-07-20T21:35:55.436433Z"
    },
    {
      "symbol": "ABNB",
      "name": "Airbnb, Inc.",
      "price": 144.94,
      "prev_close": 145.5,
      "change": -0.56,
      "change_pct": -0.38,
      "currency": "USD",
      "market": "US",
      "updated_at": "2026-07-20T21:35:56.362152Z"
    },
    {
      "symbol": "SNOW",
      "name": "Snowflake Inc.",
      "price": 274.34,
      "prev_close": 268.06,
      "change": 6.28,
      "change_pct": 2.34,
      "currency": "USD",
      "market": "US",
      "updated_at": "2026-07-20T21:35:57.305878Z"
    },
    {
      "symbol": "PLTR",
      "name": "Palantir Technologies Inc.",
      "price": 134.85,
      "prev_close": 131.68,
      "change": 3.17,
      "change_pct": 2.41,
      "currency": "USD",
      "market": "US",
      "updated_at": "2026-07-20T21:35:59.391181Z"
    },
    {
      "symbol": "COIN",
      "name": "Coinbase Global, Inc.",
      "price": 160.43,
      "prev_close": 157.29,
      "change": 3.14,
      "change_pct": 2.0,
      "currency": "USD",
      "market": "US",
      "updated_at": "2026-07-20T21:36:00.175055Z"
    },
    {
      "symbol": "SHOP",
      "name": "Shopify Inc.",
      "price": 124.48,
      "prev_close": 123.6,
      "change": 0.88,
      "change_pct": 0.71,
      "currency": "USD",
      "market": "US",
      "updated_at": "2026-07-20T21:36:01.037862Z"
    },
    {
      "symbol": "ZM",
      "name": "Zoom Communications, Inc.",
      "price": 90.91,
      "prev_close": 90.07,
      "change": 0.84,
      "change_pct": 0.93,
      "currency": "USD",
      "market": "US",
      "updated_at": "2026-07-20T21:36:02.356716Z"
    },
    {
      "symbol": "ROKU",
      "name": "Roku, Inc.",
      "price": 144.13,
      "prev_close": 143.0,
      "change": 1.13,
      "change_pct": 0.79,
      "currency": "USD",
      "market": "US",
      "updated_at": "2026-07-20T21:36:03.190170Z"
    },
    {
      "symbol": "RBLX",
      "name": "Roblox Corporation",
      "price": 53.25,
      "prev_close": 51.5,
      "change": 1.75,
      "change_pct": 3.4,
      "currency": "USD",
      "market": "US",
      "updated_at": "2026-07-20T21:36:05.153333Z"
    },
    {
      "symbol": "HOOD",
      "name": "Robinhood Markets, Inc.",
      "price": 99.28,
      "prev_close": 99.7,
      "change": -0.42,
      "change_pct": -0.42,
      "currency": "USD",
      "market": "US",
      "updated_at": "2026-07-20T21:36:06.047585Z"
    },
    {
      "symbol": "RIVN",
      "name": "Rivian Automotive, Inc.",
      "price": 17.24,
      "prev_close": 17.41,
      "change": -0.17,
      "change_pct": -0.98,
      "currency": "USD",
      "market": "US",
      "updated_at": "2026-07-20T21:36:06.817473Z"
    },
    {
      "symbol": "LCID",
      "name": "Lucid Group, Inc.",
      "price": 7.11,
      "prev_close": 7.18,
      "change": -0.07,
      "change_pct": -0.97,
      "currency": "USD",
      "market": "US",
      "updated_at": "2026-07-20T21:36:07.714236Z"
    },
    {
      "symbol": "SPY",
      "name": "State Street SPDR S&P 500 ETF Trust",
      "price": 742.09,
      "prev_close": 742.49,
      "change": -0.4,
      "change_pct": -0.05,
      "currency": "USD",
      "market": "US",
      "updated_at": "2026-07-20T21:36:08.650201Z"
    },
    {
      "symbol": "QQQ",
      "name": "Invesco QQQ Trust",
      "price": 696.06,
      "prev_close": 693.76,
      "change": 2.3,
      "change_pct": 0.33,
      "currency": "USD",
      "market": "US",
      "updated_at": "2026-07-20T21:36:09.803295Z"
    },
    {
      "symbol": "DIA",
      "name": "State Street SPDR Dow Jones Industrial A",
      "price": 517.94,
      "prev_close": 520.54,
      "change": -2.6,
      "change_pct": -0.5,
      "currency": "USD",
      "market": "US",
      "updated_at": "2026-07-20T21:36:10.748500Z"
    },
    {
      "symbol": "VTI",
      "name": "Vanguard Total Stock Market Index Fund E",
      "price": 366.25,
      "prev_close": 366.99,
      "change": -0.74,
      "change_pct": -0.2,
      "currency": "USD",
      "market": "US",
      "updated_at": "2026-07-20T21:36:11.574847Z"
    },
    {
      "symbol": "IWM",
      "name": "iShares Russell 2000 ETF",
      "price": 292.31,
      "prev_close": 293.49,
      "change": -1.18,
      "change_pct": -0.4,
      "currency": "USD",
      "market": "US",
      "updated_at": "2026-07-20T21:36:12.649999Z"
    },
    {
      "symbol": "TSM",
      "name": "Taiwan Semiconductor Manufacturing Compa",
      "price": 402.3,
      "prev_close": 397.72,
      "change": 4.58,
      "change_pct": 1.15,
      "currency": "USD",
      "market": "US",
      "updated_at": "2026-07-20T21:36:13.534167Z"
    },
    {
      "symbol": "UMC",
      "name": "United Microelectronics Corporation",
      "price": 20.3,
      "prev_close": 21.43,
      "change": -1.13,
      "change_pct": -5.27,
      "currency": "USD",
      "market": "US",
      "updated_at": "2026-07-20T21:36:14.336515Z"
    }
  ],
  "tw_stocks": [
    {
      "symbol": "2330",
      "name": "Taiwan Semiconductor",
      "price": 2320.0,
      "prev_close": 2320.0,
      "change": 0.0,
      "change_pct": 0.0,
      "currency": "TWD",
      "market": "TW",
      "updated_at": "2026-07-20T21:36:17.988611Z"
    },
    {
      "symbol": "2317",
      "name": "Hon Hai Precision In",
      "price": 234.5,
      "prev_close": 234.0,
      "change": 0.5,
      "change_pct": 0.21,
      "currency": "TWD",
      "market": "TW",
      "updated_at": "2026-07-20T21:36:19.313441Z"
    },
    {
      "symbol": "2454",
      "name": "MediaTek Inc.",
      "price": 3340.0,
      "prev_close": 3395.0,
      "change": -55.0,
      "change_pct": -1.62,
      "currency": "TWD",
      "market": "TW",
      "updated_at": "2026-07-20T21:36:20.297288Z"
    },
    {
      "symbol": "2382",
      "name": "Quanta Computer Inc.",
      "price": 316.0,
      "prev_close": 327.5,
      "change": -11.5,
      "change_pct": -3.51,
      "currency": "TWD",
      "market": "TW",
      "updated_at": "2026-07-20T21:36:21.560966Z"
    },
    {
      "symbol": "2308",
      "name": "Delta Electronics, I",
      "price": 1705.0,
      "prev_close": 1745.0,
      "change": -40.0,
      "change_pct": -2.29,
      "currency": "TWD",
      "market": "TW",
      "updated_at": "2026-07-20T21:36:22.473931Z"
    },
    {
      "symbol": "2303",
      "name": "United Microelectron",
      "price": 130.0,
      "prev_close": 144.0,
      "change": -14.0,
      "change_pct": -9.72,
      "currency": "TWD",
      "market": "TW",
      "updated_at": "2026-07-20T21:36:23.386412Z"
    },
    {
      "symbol": "2881",
      "name": "Fubon Financial Hold",
      "price": 123.5,
      "prev_close": 123.5,
      "change": 0.0,
      "change_pct": 0.0,
      "currency": "TWD",
      "market": "TW",
      "updated_at": "2026-07-20T21:36:24.444913Z"
    },
    {
      "symbol": "2882",
      "name": "Cathay Financial Hol",
      "price": 94.0,
      "prev_close": 95.2,
      "change": -1.2,
      "change_pct": -1.26,
      "currency": "TWD",
      "market": "TW",
      "updated_at": "2026-07-20T21:36:25.467834Z"
    },
    {
      "symbol": "2891",
      "name": "CTBC Financial Holdi",
      "price": 61.5,
      "prev_close": 61.6,
      "change": -0.1,
      "change_pct": -0.16,
      "currency": "TWD",
      "market": "TW",
      "updated_at": "2026-07-20T21:36:26.335700Z"
    },
    {
      "symbol": "2886",
      "name": "Mega Financial Holdi",
      "price": 48.2,
      "prev_close": 47.1,
      "change": 1.1,
      "change_pct": 2.34,
      "currency": "TWD",
      "market": "TW",
      "updated_at": "2026-07-20T21:36:27.140916Z"
    },
    {
      "symbol": "2884",
      "name": "E.SUN Financial Hold",
      "price": 35.85,
      "prev_close": 35.1,
      "change": 0.75,
      "change_pct": 2.14,
      "currency": "TWD",
      "market": "TW",
      "updated_at": "2026-07-20T21:36:29.153235Z"
    },
    {
      "symbol": "2885",
      "name": "Yuanta Financial Hol",
      "price": 62.9,
      "prev_close": 64.9,
      "change": -2.0,
      "change_pct": -3.08,
      "currency": "TWD",
      "market": "TW",
      "updated_at": "2026-07-20T21:36:30.398577Z"
    },
    {
      "symbol": "2892",
      "name": "First Financial Hold",
      "price": 33.95,
      "prev_close": 33.9,
      "change": 0.05,
      "change_pct": 0.15,
      "currency": "TWD",
      "market": "TW",
      "updated_at": "2026-07-20T21:36:31.181136Z"
    },
    {
      "symbol": "2883",
      "name": "KGI Financial Holdin",
      "price": 29.55,
      "prev_close": 29.95,
      "change": -0.4,
      "change_pct": -1.34,
      "currency": "TWD",
      "market": "TW",
      "updated_at": "2026-07-20T21:36:32.173737Z"
    },
    {
      "symbol": "2887",
      "name": "TS Financial Holding",
      "price": 34.8,
      "prev_close": 35.15,
      "change": -0.35,
      "change_pct": -1.0,
      "currency": "TWD",
      "market": "TW",
      "updated_at": "2026-07-20T21:36:33.003794Z"
    },
    {
      "symbol": "2412",
      "name": "Chunghwa Telecom Co.",
      "price": 139.0,
      "prev_close": 138.0,
      "change": 1.0,
      "change_pct": 0.72,
      "currency": "TWD",
      "market": "TW",
      "updated_at": "2026-07-20T21:36:35.884625Z"
    },
    {
      "symbol": "2002",
      "name": "China Steel Corporat",
      "price": 18.55,
      "prev_close": 18.65,
      "change": -0.1,
      "change_pct": -0.54,
      "currency": "TWD",
      "market": "TW",
      "updated_at": "2026-07-20T21:36:36.823022Z"
    },
    {
      "symbol": "1301",
      "name": "Formosa Plastics Cor",
      "price": 60.6,
      "prev_close": 62.4,
      "change": -1.8,
      "change_pct": -2.88,
      "currency": "TWD",
      "market": "TW",
      "updated_at": "2026-07-20T21:36:37.747010Z"
    },
    {
      "symbol": "1303",
      "name": "Nan Ya Plastics Corp",
      "price": 186.5,
      "prev_close": 199.0,
      "change": -12.5,
      "change_pct": -6.28,
      "currency": "TWD",
      "market": "TW",
      "updated_at": "2026-07-20T21:36:38.586391Z"
    },
    {
      "symbol": "1326",
      "name": "Formosa Chemicals & ",
      "price": 64.2,
      "prev_close": 65.7,
      "change": -1.5,
      "change_pct": -2.28,
      "currency": "TWD",
      "market": "TW",
      "updated_at": "2026-07-20T21:36:40.686728Z"
    },
    {
      "symbol": "2207",
      "name": "Hotai Motor Co.,Ltd.",
      "price": 490.0,
      "prev_close": 488.5,
      "change": 1.5,
      "change_pct": 0.31,
      "currency": "TWD",
      "market": "TW",
      "updated_at": "2026-07-20T21:36:41.538418Z"
    },
    {
      "symbol": "2357",
      "name": "ASUSTeK Computer Inc",
      "price": 688.0,
      "prev_close": 705.0,
      "change": -17.0,
      "change_pct": -2.41,
      "currency": "TWD",
      "market": "TW",
      "updated_at": "2026-07-20T21:36:42.384284Z"
    },
    {
      "symbol": "2379",
      "name": "Realtek Semiconducto",
      "price": 709.0,
      "prev_close": 720.0,
      "change": -11.0,
      "change_pct": -1.53,
      "currency": "TWD",
      "market": "TW",
      "updated_at": "2026-07-20T21:36:43.168010Z"
    },
    {
      "symbol": "2395",
      "name": "Advantech Co., Ltd.",
      "price": 516.0,
      "prev_close": 505.0,
      "change": 11.0,
      "change_pct": 2.18,
      "currency": "TWD",
      "market": "TW",
      "updated_at": "2026-07-20T21:36:44.138543Z"
    },
    {
      "symbol": "3711",
      "name": "ASE Technology Holdi",
      "price": 597.0,
      "prev_close": 614.0,
      "change": -17.0,
      "change_pct": -2.77,
      "currency": "TWD",
      "market": "TW",
      "updated_at": "2026-07-20T21:36:44.990785Z"
    },
    {
      "symbol": "2376",
      "name": "Giga-Byte Technology",
      "price": 331.0,
      "prev_close": 324.0,
      "change": 7.0,
      "change_pct": 2.16,
      "currency": "TWD",
      "market": "TW",
      "updated_at": "2026-07-20T21:36:45.793588Z"
    },
    {
      "symbol": "2408",
      "name": "Nanya Technology Cor",
      "price": 381.0,
      "prev_close": 395.5,
      "change": -14.5,
      "change_pct": -3.67,
      "currency": "TWD",
      "market": "TW",
      "updated_at": "2026-07-20T21:36:46.749264Z"
    },
    {
      "symbol": "3008",
      "name": "Largan Precision Co.",
      "price": 3875.0,
      "prev_close": 4010.0,
      "change": -135.0,
      "change_pct": -3.37,
      "currency": "TWD",
      "market": "TW",
      "updated_at": "2026-07-20T21:36:47.774896Z"
    },
    {
      "symbol": "2327",
      "name": "Yageo Corporation",
      "price": 630.0,
      "prev_close": 699.0,
      "change": -69.0,
      "change_pct": -9.87,
      "currency": "TWD",
      "market": "TW",
      "updated_at": "2026-07-20T21:36:49.161692Z"
    },
    {
      "symbol": "4938",
      "name": "Pegatron Corporation",
      "price": 80.0,
      "prev_close": 82.5,
      "change": -2.5,
      "change_pct": -3.03,
      "currency": "TWD",
      "market": "TW",
      "updated_at": "2026-07-20T21:36:51.076943Z"
    },
    {
      "symbol": "2337",
      "name": "Macronix Internation",
      "price": 117.5,
      "prev_close": 125.0,
      "change": -7.5,
      "change_pct": -6.0,
      "currency": "TWD",
      "market": "TW",
      "updated_at": "2026-07-20T21:36:51.999553Z"
    },
    {
      "symbol": "2344",
      "name": "Winbond Electronics ",
      "price": 151.0,
      "prev_close": 155.0,
      "change": -4.0,
      "change_pct": -2.58,
      "currency": "TWD",
      "market": "TW",
      "updated_at": "2026-07-20T21:36:52.914622Z"
    },
    {
      "symbol": "2345",
      "name": "Accton Technology Co",
      "price": 2090.0,
      "prev_close": 2100.0,
      "change": -10.0,
      "change_pct": -0.48,
      "currency": "TWD",
      "market": "TW",
      "updated_at": "2026-07-20T21:36:54.065070Z"
    },
    {
      "symbol": "3034",
      "name": "Novatek Microelectro",
      "price": 458.0,
      "prev_close": 465.0,
      "change": -7.0,
      "change_pct": -1.51,
      "currency": "TWD",
      "market": "TW",
      "updated_at": "2026-07-20T21:36:54.905716Z"
    },
    {
      "symbol": "3037",
      "name": "Unimicron Technology",
      "price": 750.0,
      "prev_close": 794.0,
      "change": -44.0,
      "change_pct": -5.54,
      "currency": "TWD",
      "market": "TW",
      "updated_at": "2026-07-20T21:36:55.824905Z"
    },
    {
      "symbol": "3045",
      "name": "Taiwan Mobile Co., L",
      "price": 112.0,
      "prev_close": 111.5,
      "change": 0.5,
      "change_pct": 0.45,
      "currency": "TWD",
      "market": "TW",
      "updated_at": "2026-07-20T21:36:56.754571Z"
    },
    {
      "symbol": "3231",
      "name": "Wistron Corporation",
      "price": 143.5,
      "prev_close": 140.0,
      "change": 3.5,
      "change_pct": 2.5,
      "currency": "TWD",
      "market": "TW",
      "updated_at": "2026-07-20T21:36:57.604463Z"
    },
    {
      "symbol": "3533",
      "name": "Lotes Co., Ltd.",
      "price": 1905.0,
      "prev_close": 1865.0,
      "change": 40.0,
      "change_pct": 2.14,
      "currency": "TWD",
      "market": "TW",
      "updated_at": "2026-07-20T21:36:58.445004Z"
    },
    {
      "symbol": "4904",
      "name": "Far EasTone Telecomm",
      "price": 104.5,
      "prev_close": 104.0,
      "change": 0.5,
      "change_pct": 0.48,
      "currency": "TWD",
      "market": "TW",
      "updated_at": "2026-07-20T21:36:59.315045Z"
    },
    {
      "symbol": "5871",
      "name": "Chailease Holding Co",
      "price": 122.5,
      "prev_close": 119.5,
      "change": 3.0,
      "change_pct": 2.51,
      "currency": "TWD",
      "market": "TW",
      "updated_at": "2026-07-20T21:37:01.085329Z"
    },
    {
      "symbol": "6505",
      "name": "Formosa Petrochemica",
      "price": 77.7,
      "prev_close": 80.1,
      "change": -2.4,
      "change_pct": -3.0,
      "currency": "TWD",
      "market": "TW",
      "updated_at": "2026-07-20T21:37:01.949701Z"
    },
    {
      "symbol": "6669",
      "name": "Wiwynn Corporation",
      "price": 4685.0,
      "prev_close": 4660.0,
      "change": 25.0,
      "change_pct": 0.54,
      "currency": "TWD",
      "market": "TW",
      "updated_at": "2026-07-20T21:37:02.828816Z"
    },
    {
      "symbol": "6770",
      "name": "Powerchip Semiconduc",
      "price": 63.0,
      "prev_close": 68.9,
      "change": -5.9,
      "change_pct": -8.56,
      "currency": "TWD",
      "market": "TW",
      "updated_at": "2026-07-20T21:37:03.537430Z"
    },
    {
      "symbol": "8046",
      "name": "Nan Ya Printed Circu",
      "price": 1105.0,
      "prev_close": 1150.0,
      "change": -45.0,
      "change_pct": -3.91,
      "currency": "TWD",
      "market": "TW",
      "updated_at": "2026-07-20T21:37:04.339662Z"
    },
    {
      "symbol": "9910",
      "name": "Feng Tay Enterprises",
      "price": 68.2,
      "prev_close": 67.4,
      "change": 0.8,
      "change_pct": 1.19,
      "currency": "TWD",
      "market": "TW",
      "updated_at": "2026-07-20T21:37:05.153769Z"
    },
    {
      "symbol": "2105",
      "name": "Cheng Shin Rubber In",
      "price": 33.2,
      "prev_close": 33.7,
      "change": -0.5,
      "change_pct": -1.48,
      "currency": "TWD",
      "market": "TW",
      "updated_at": "2026-07-20T21:37:05.989053Z"
    },
    {
      "symbol": "2049",
      "name": "Hiwin Technologies C",
      "price": 300.0,
      "prev_close": 306.5,
      "change": -6.5,
      "change_pct": -2.12,
      "currency": "TWD",
      "market": "TW",
      "updated_at": "2026-07-20T21:37:07.036703Z"
    },
    {
      "symbol": "2915",
      "name": "Ruentex Industries L",
      "price": 51.1,
      "prev_close": 50.9,
      "change": 0.2,
      "change_pct": 0.39,
      "currency": "TWD",
      "market": "TW",
      "updated_at": "2026-07-20T21:37:08.109241Z"
    },
    {
      "symbol": "1216",
      "name": "Uni-President Enterp",
      "price": 80.3,
      "prev_close": 79.5,
      "change": 0.8,
      "change_pct": 1.01,
      "currency": "TWD",
      "market": "TW",
      "updated_at": "2026-07-20T21:37:09.056860Z"
    },
    {
      "symbol": "2801",
      "name": "Chang Hwa Commercial",
      "price": 23.85,
      "prev_close": 23.75,
      "change": 0.1,
      "change_pct": 0.42,
      "currency": "TWD",
      "market": "TW",
      "updated_at": "2026-07-20T21:37:11.011831Z"
    },
    {
      "symbol": "1402",
      "name": "Far Eastern New Cent",
      "price": 27.3,
      "prev_close": 27.75,
      "change": -0.45,
      "change_pct": -1.62,
      "currency": "TWD",
      "market": "TW",
      "updated_at": "2026-07-20T21:37:12.063525Z"
    },
    {
      "symbol": "1101",
      "name": "TCC Group Holdings C",
      "price": 23.8,
      "prev_close": 23.6,
      "change": 0.2,
      "change_pct": 0.85,
      "currency": "TWD",
      "market": "TW",
      "updated_at": "2026-07-20T21:37:12.959224Z"
    },
    {
      "symbol": "1102",
      "name": "Asia Cement Corporat",
      "price": 33.0,
      "prev_close": 33.2,
      "change": -0.2,
      "change_pct": -0.6,
      "currency": "TWD",
      "market": "TW",
      "updated_at": "2026-07-20T21:37:14.216001Z"
    },
    {
      "symbol": "2912",
      "name": "President Chain Stor",
      "price": 243.5,
      "prev_close": 240.5,
      "change": 3.0,
      "change_pct": 1.25,
      "currency": "TWD",
      "market": "TW",
      "updated_at": "2026-07-20T21:37:15.216185Z"
    },
    {
      "symbol": "2880",
      "name": "Hua Nan Financial Ho",
      "price": 39.9,
      "prev_close": 39.9,
      "change": 0.0,
      "change_pct": 0.0,
      "currency": "TWD",
      "market": "TW",
      "updated_at": "2026-07-20T21:37:17.672667Z"
    },
    {
      "symbol": "5880",
      "name": "Taiwan Cooperative F",
      "price": 25.5,
      "prev_close": 25.4,
      "change": 0.1,
      "change_pct": 0.39,
      "currency": "TWD",
      "market": "TW",
      "updated_at": "2026-07-20T21:37:18.516508Z"
    },
    {
      "symbol": "2474",
      "name": "Catcher Technology C",
      "price": 190.0,
      "prev_close": 186.5,
      "change": 3.5,
      "change_pct": 1.88,
      "currency": "TWD",
      "market": "TW",
      "updated_at": "2026-07-20T21:37:19.454969Z"
    },
    {
      "symbol": "2352",
      "name": "Qisda Corporation",
      "price": 29.85,
      "prev_close": 30.55,
      "change": -0.7,
      "change_pct": -2.29,
      "currency": "TWD",
      "market": "TW",
      "updated_at": "2026-07-20T21:37:20.398071Z"
    },
    {
      "symbol": "2301",
      "name": "Lite-On Technology C",
      "price": 193.5,
      "prev_close": 197.0,
      "change": -3.5,
      "change_pct": -1.78,
      "currency": "TWD",
      "market": "TW",
      "updated_at": "2026-07-20T21:37:22.257928Z"
    },
    {
      "symbol": "2356",
      "name": "Inventec Corporation",
      "price": 57.2,
      "prev_close": 58.6,
      "change": -1.4,
      "change_pct": -2.39,
      "currency": "TWD",
      "market": "TW",
      "updated_at": "2026-07-20T21:37:23.148098Z"
    },
    {
      "symbol": "2324",
      "name": "Compal Electronics, ",
      "price": 34.4,
      "prev_close": 35.85,
      "change": -1.45,
      "change_pct": -4.04,
      "currency": "TWD",
      "market": "TW",
      "updated_at": "2026-07-20T21:37:24.269897Z"
    },
    {
      "symbol": "2353",
      "name": "Acer Incorporated",
      "price": 29.25,
      "prev_close": 29.55,
      "change": -0.3,
      "change_pct": -1.02,
      "currency": "TWD",
      "market": "TW",
      "updated_at": "2026-07-20T21:37:25.192390Z"
    },
    {
      "symbol": "2360",
      "name": "Chroma ATE Inc.",
      "price": 1835.0,
      "prev_close": 1865.0,
      "change": -30.0,
      "change_pct": -1.61,
      "currency": "TWD",
      "market": "TW",
      "updated_at": "2026-07-20T21:37:26.132937Z"
    },
    {
      "symbol": "2347",
      "name": "Synnex Technology In",
      "price": 84.0,
      "prev_close": 86.3,
      "change": -2.3,
      "change_pct": -2.67,
      "currency": "TWD",
      "market": "TW",
      "updated_at": "2026-07-20T21:37:27.070731Z"
    },
    {
      "symbol": "2385",
      "name": "Chicony Electronics ",
      "price": 102.5,
      "prev_close": 103.0,
      "change": -0.5,
      "change_pct": -0.49,
      "currency": "TWD",
      "market": "TW",
      "updated_at": "2026-07-20T21:37:28.065680Z"
    },
    {
      "symbol": "3006",
      "name": "Elite Semiconductor ",
      "price": 188.5,
      "prev_close": 198.0,
      "change": -9.5,
      "change_pct": -4.8,
      "currency": "TWD",
      "market": "TW",
      "updated_at": "2026-07-20T21:37:28.923087Z"
    },
    {
      "symbol": "4958",
      "name": "Zhen Ding Technology",
      "price": 478.5,
      "prev_close": 521.0,
      "change": -42.5,
      "change_pct": -8.16,
      "currency": "TWD",
      "market": "TW",
      "updated_at": "2026-07-20T21:37:30.830707Z"
    },
    {
      "symbol": "6176",
      "name": "Radiant Opto-Electro",
      "price": 83.1,
      "prev_close": 84.6,
      "change": -1.5,
      "change_pct": -1.77,
      "currency": "TWD",
      "market": "TW",
      "updated_at": "2026-07-20T21:37:33.744981Z"
    },
    {
      "symbol": "6153",
      "name": "Career Technology (M",
      "price": 16.4,
      "prev_close": 17.05,
      "change": -0.65,
      "change_pct": -3.81,
      "currency": "TWD",
      "market": "TW",
      "updated_at": "2026-07-20T21:37:34.641500Z"
    },
    {
      "symbol": "6202",
      "name": "Holtek Semiconductor",
      "price": 56.1,
      "prev_close": 57.7,
      "change": -1.6,
      "change_pct": -2.77,
      "currency": "TWD",
      "market": "TW",
      "updated_at": "2026-07-20T21:37:35.450700Z"
    },
    {
      "symbol": "6239",
      "name": "Powertech Technology",
      "price": 266.5,
      "prev_close": 287.0,
      "change": -20.5,
      "change_pct": -7.14,
      "currency": "TWD",
      "market": "TW",
      "updated_at": "2026-07-20T21:37:36.306937Z"
    },
    {
      "symbol": "6415",
      "name": "Silergy Corp.",
      "price": 427.5,
      "prev_close": 434.5,
      "change": -7.0,
      "change_pct": -1.61,
      "currency": "TWD",
      "market": "TW",
      "updated_at": "2026-07-20T21:37:37.155788Z"
    },
    {
      "symbol": "6451",
      "name": "ShunSin Technology H",
      "price": 395.5,
      "prev_close": 429.5,
      "change": -34.0,
      "change_pct": -7.92,
      "currency": "TWD",
      "market": "TW",
      "updated_at": "2026-07-20T21:37:37.930945Z"
    },
    {
      "symbol": "6657",
      "name": "Energenesis Biomedic",
      "price": 34.5,
      "prev_close": 33.85,
      "change": 0.65,
      "change_pct": 1.92,
      "currency": "TWD",
      "market": "TW",
      "updated_at": "2026-07-20T21:37:41.187301Z"
    },
    {
      "symbol": "2609",
      "name": "Yang Ming Marine Tra",
      "price": 49.0,
      "prev_close": 49.3,
      "change": -0.3,
      "change_pct": -0.61,
      "currency": "TWD",
      "market": "TW",
      "updated_at": "2026-07-20T21:37:43.116457Z"
    },
    {
      "symbol": "2615",
      "name": "Wan Hai Lines Ltd.",
      "price": 80.5,
      "prev_close": 79.8,
      "change": 0.7,
      "change_pct": 0.88,
      "currency": "TWD",
      "market": "TW",
      "updated_at": "2026-07-20T21:37:44.007257Z"
    },
    {
      "symbol": "2618",
      "name": "EVA Airways Corp.",
      "price": 41.2,
      "prev_close": 41.3,
      "change": -0.1,
      "change_pct": -0.24,
      "currency": "TWD",
      "market": "TW",
      "updated_at": "2026-07-20T21:37:44.892305Z"
    },
    {
      "symbol": "2603",
      "name": "Evergreen Marine Cor",
      "price": 196.0,
      "prev_close": 199.0,
      "change": -3.0,
      "change_pct": -1.51,
      "currency": "TWD",
      "market": "TW",
      "updated_at": "2026-07-20T21:37:45.915933Z"
    },
    {
      "symbol": "2605",
      "name": "Sincere Navigation C",
      "price": 30.65,
      "prev_close": 30.8,
      "change": -0.15,
      "change_pct": -0.49,
      "currency": "TWD",
      "market": "TW",
      "updated_at": "2026-07-20T21:37:46.795709Z"
    },
    {
      "symbol": "2606",
      "name": "U-Ming Marine Transp",
      "price": 61.6,
      "prev_close": 61.2,
      "change": 0.4,
      "change_pct": 0.65,
      "currency": "TWD",
      "market": "TW",
      "updated_at": "2026-07-20T21:37:47.705734Z"
    },
    {
      "symbol": "2610",
      "name": "China Airlines, Ltd.",
      "price": 20.95,
      "prev_close": 20.7,
      "change": 0.25,
      "change_pct": 1.21,
      "currency": "TWD",
      "market": "TW",
      "updated_at": "2026-07-20T21:37:48.526032Z"
    },
    {
      "symbol": "1904",
      "name": "Cheng Loong Corporat",
      "price": 21.35,
      "prev_close": 21.95,
      "change": -0.6,
      "change_pct": -2.73,
      "currency": "TWD",
      "market": "TW",
      "updated_at": "2026-07-20T21:37:50.610912Z"
    },
    {
      "symbol": "1907",
      "name": "YFY Inc.",
      "price": 27.75,
      "prev_close": 28.1,
      "change": -0.35,
      "change_pct": -1.25,
      "currency": "TWD",
      "market": "TW",
      "updated_at": "2026-07-20T21:37:51.448953Z"
    },
    {
      "symbol": "2101",
      "name": "Nankang Rubber Tire ",
      "price": 33.5,
      "prev_close": 33.95,
      "change": -0.45,
      "change_pct": -1.33,
      "currency": "TWD",
      "market": "TW",
      "updated_at": "2026-07-20T21:37:53.332843Z"
    },
    {
      "symbol": "2103",
      "name": "TSRC Corporation",
      "price": 23.05,
      "prev_close": 23.5,
      "change": -0.45,
      "change_pct": -1.91,
      "currency": "TWD",
      "market": "TW",
      "updated_at": "2026-07-20T21:37:54.696202Z"
    },
    {
      "symbol": "1590",
      "name": "Airtac International",
      "price": 1335.0,
      "prev_close": 1260.0,
      "change": 75.0,
      "change_pct": 5.95,
      "currency": "TWD",
      "market": "TW",
      "updated_at": "2026-07-20T21:37:55.602936Z"
    },
    {
      "symbol": "6271",
      "name": "Tong Hsing Electroni",
      "price": 192.5,
      "prev_close": 203.5,
      "change": -11.0,
      "change_pct": -5.41,
      "currency": "TWD",
      "market": "TW",
      "updated_at": "2026-07-20T21:37:57.843353Z"
    },
    {
      "symbol": "6278",
      "name": "Taiwan Surface Mount",
      "price": 157.5,
      "prev_close": 165.0,
      "change": -7.5,
      "change_pct": -4.55,
      "currency": "TWD",
      "market": "TW",
      "updated_at": "2026-07-20T21:37:58.673331Z"
    }
  ],
  "us_count": 96,
  "tw_count": 88,
  "updated_at": "2026-07-20T21:38:00.629675Z"
}